<?xml version="1.0" encoding="utf-8"?>
<detectors>
	<detector id="0">
		<volume>0.8</volume>
		<coor>[31.898038207503802, 118.76301495332072]</coor>
	</detector>
	<detector id="1">
		<volume>0.8</volume>
		<coor>[31.89801762251141, 118.76248645996218]</coor>
	</detector>
	<detector id="2">
		<volume>0.8</volume>
		<coor>[31.897997037519012, 118.76195796660363]</coor>
	</detector>
	<detector id="3">
		<volume>1.4</volume>
		<coor>[31.89797645252662, 118.76142947324507]</coor>
	</detector>
	<detector id="4">
		<volume>5.0</volume>
		<coor>[31.897955867534222, 118.76090097988651]</coor>
	</detector>
	<detector id="5">
		<volume>9.6</volume>
		<coor>[31.897940337519014, 118.76050226660362]</coor>
	</detector>
	<detector id="6">
		<volume>0.8</volume>
		<coor>[31.898372937389837, 118.76647524557171]</coor>
	</detector>
	<detector id="7">
		<volume>0.8</volume>
		<coor>[31.89831961216951, 118.76594993671512]</coor>
	</detector>
	<detector id="8">
		<volume>0.8</volume>
		<coor>[31.89826628694918, 118.76542462785852]</coor>
	</detector>
	<detector id="9">
		<volume>1.4</volume>
		<coor>[31.898212961728852, 118.76489931900194]</coor>
	</detector>
	<detector id="10">
		<volume>5.0</volume>
		<coor>[31.898159636508527, 118.76437401014536]</coor>
	</detector>
	<detector id="11">
		<volume>9.6</volume>
		<coor>[31.8981063112882, 118.76384870128877]</coor>
	</detector>
	<detector id="12">
		<volume>0.5</volume>
		<coor>[31.89806407433902, 118.76343262343025]</coor>
	</detector>
	<detector id="13">
		<volume>0.8</volume>
		<coor>[31.89989044742388, 118.769530369057]</coor>
	</detector>
	<detector id="14">
		<volume>0.8</volume>
		<coor>[31.899651342271625, 118.76908250717096]</coor>
	</detector>
	<detector id="15">
		<volume>0.8</volume>
		<coor>[31.899412237119375, 118.76863464528495]</coor>
	</detector>
	<detector id="16">
		<volume>1.4</volume>
		<coor>[31.899173131967125, 118.76818678339893]</coor>
	</detector>
	<detector id="17">
		<volume>5.0</volume>
		<coor>[31.89893402681487, 118.7677389215129]</coor>
	</detector>
	<detector id="18">
		<volume>9.6</volume>
		<coor>[31.898694921662624, 118.76729105962687]</coor>
	</detector>
	<detector id="19">
		<volume>0.5</volume>
		<coor>[31.89848748454325, 118.76690251434192]</coor>
	</detector>
	<detector id="20">
		<volume>0.8</volume>
		<coor>[31.90451796628657, 118.7769930983891]</coor>
	</detector>
	<detector id="21">
		<volume>0.8</volume>
		<coor>[31.904252298859703, 118.7765664951673]</coor>
	</detector>
	<detector id="22">
		<volume>0.8</volume>
		<coor>[31.903986631432844, 118.7761398919455]</coor>
	</detector>
	<detector id="23">
		<volume>1.4</volume>
		<coor>[31.90372096400598, 118.77571328872371]</coor>
	</detector>
	<detector id="24">
		<volume>5.0</volume>
		<coor>[31.903455296579118, 118.77528668550191]</coor>
	</detector>
	<detector id="25">
		<volume>9.6</volume>
		<coor>[31.90318962915226, 118.7748600822801]</coor>
	</detector>
	<detector id="26">
		<volume>0.5</volume>
		<coor>[31.902923961725392, 118.7744334790583]</coor>
	</detector>
	<detector id="27">
		<volume>0.5</volume>
		<coor>[31.902658294298533, 118.7740068758365]</coor>
	</detector>
	<detector id="28">
		<volume>0.5</volume>
		<coor>[31.902392626871666, 118.77358027261471]</coor>
	</detector>
	<detector id="29">
		<volume>0.5</volume>
		<coor>[31.902126959444807, 118.77315366939291]</coor>
	</detector>
	<detector id="30">
		<volume>0.5</volume>
		<coor>[31.90186129201794, 118.77272706617111]</coor>
	</detector>
	<detector id="31">
		<volume>0.5</volume>
		<coor>[31.90159562459108, 118.77230046294932]</coor>
	</detector>
	<detector id="32">
		<volume>7.3</volume>
		<coor>[31.901329957164222, 118.77187385972752]</coor>
	</detector>
	<detector id="33">
		<volume>0.5</volume>
		<coor>[31.901064289737356, 118.77144725650572]</coor>
	</detector>
	<detector id="34">
		<volume>0.5</volume>
		<coor>[31.900798622310496, 118.77102065328393]</coor>
	</detector>
	<detector id="35">
		<volume>0.5</volume>
		<coor>[31.90053295488363, 118.77059405006213]</coor>
	</detector>
	<detector id="36">
		<volume>0.5</volume>
		<coor>[31.90026728745677, 118.77016744684033]</coor>
	</detector>
	<detector id="37">
		<volume>1.4</volume>
		<coor>[31.90007222687167, 118.76985422261473]</coor>
	</detector>
	<detector id="38">
		<volume>0.8</volume>
		<coor>[31.88633682221687, 118.78400134824307]</coor>
	</detector>
	<detector id="39">
		<volume>0.8</volume>
		<coor>[31.886670666650602, 118.78364744472921]</coor>
	</detector>
	<detector id="40">
		<volume>0.8</volume>
		<coor>[31.887004511084342, 118.78329354121536]</coor>
	</detector>
	<detector id="41">
		<volume>1.4</volume>
		<coor>[31.887338355518075, 118.7829396377015]</coor>
	</detector>
	<detector id="42">
		<volume>5.0</volume>
		<coor>[31.887672199951815, 118.78258573418765]</coor>
	</detector>
	<detector id="43">
		<volume>9.6</volume>
		<coor>[31.88800604438555, 118.7822318306738]</coor>
	</detector>
	<detector id="44">
		<volume>0.5</volume>
		<coor>[31.88833988881929, 118.78187792715995]</coor>
	</detector>
	<detector id="45">
		<volume>0.5</volume>
		<coor>[31.88867373325302, 118.7815240236461]</coor>
	</detector>
	<detector id="46">
		<volume>0.5</volume>
		<coor>[31.889007577686762, 118.78117012013224]</coor>
	</detector>
	<detector id="47">
		<volume>0.5</volume>
		<coor>[31.889341422120495, 118.78081621661839]</coor>
	</detector>
	<detector id="48">
		<volume>0.5</volume>
		<coor>[31.889675266554235, 118.78046231310454]</coor>
	</detector>
	<detector id="49">
		<volume>0.5</volume>
		<coor>[31.890009110987968, 118.78010840959068]</coor>
	</detector>
	<detector id="50">
		<volume>7.3</volume>
		<coor>[31.89034295542171, 118.77975450607683]</coor>
	</detector>
	<detector id="51">
		<volume>0.5</volume>
		<coor>[31.89067679985544, 118.77940060256297]</coor>
	</detector>
	<detector id="52">
		<volume>0.5</volume>
		<coor>[31.89101064428918, 118.77904669904912]</coor>
	</detector>
	<detector id="53">
		<volume>0.5</volume>
		<coor>[31.89134448872292, 118.77869279553526]</coor>
	</detector>
	<detector id="54">
		<volume>0.5</volume>
		<coor>[31.891678333156655, 118.77833889202142]</coor>
	</detector>
	<detector id="55">
		<volume>1.4</volume>
		<coor>[31.892012177590395, 118.77798498850757]</coor>
	</detector>
	<detector id="56">
		<volume>10.7</volume>
		<coor>[31.892346022024128, 118.77763108499371]</coor>
	</detector>
	<detector id="57">
		<volume>12.2</volume>
		<coor>[31.89267986645787, 118.77727718147986]</coor>
	</detector>
	<detector id="58">
		<volume>0.5</volume>
		<coor>[31.8930137108916, 118.776923277966]</coor>
	</detector>
	<detector id="59">
		<volume>0.5</volume>
		<coor>[31.89334755532534, 118.77656937445215]</coor>
	</detector>
	<detector id="60">
		<volume>0.5</volume>
		<coor>[31.893681399759075, 118.7762154709383]</coor>
	</detector>
	<detector id="61">
		<volume>0.5</volume>
		<coor>[31.894015244192815, 118.77586156742444]</coor>
	</detector>
	<detector id="62">
		<volume>0.5</volume>
		<coor>[31.894349088626548, 118.77550766391059]</coor>
	</detector>
	<detector id="63">
		<volume>0.5</volume>
		<coor>[31.894682933060288, 118.77515376039673]</coor>
	</detector>
	<detector id="64">
		<volume>0.5</volume>
		<coor>[31.89501677749402, 118.77479985688288]</coor>
	</detector>
	<detector id="65">
		<volume>0.5</volume>
		<coor>[31.89535062192776, 118.77444595336902]</coor>
	</detector>
	<detector id="66">
		<volume>0.5</volume>
		<coor>[31.895578672072315, 118.77420420080605]</coor>
	</detector>
	<detector id="67">
		<volume>0.8</volume>
		<coor>[31.895810755546677, 118.7739678618955]</coor>
	</detector>
	<detector id="68">
		<volume>0.8</volume>
		<coor>[31.896152666640027, 118.77362478568652]</coor>
	</detector>
	<detector id="69">
		<volume>0.8</volume>
		<coor>[31.89649457773338, 118.77328170947754]</coor>
	</detector>
	<detector id="70">
		<volume>1.4</volume>
		<coor>[31.896836488826732, 118.77293863326855]</coor>
	</detector>
	<detector id="71">
		<volume>5.0</volume>
		<coor>[31.897178399920087, 118.77259555705956]</coor>
	</detector>
	<detector id="72">
		<volume>9.6</volume>
		<coor>[31.897520311013437, 118.7722524808506]</coor>
	</detector>
	<detector id="73">
		<volume>0.5</volume>
		<coor>[31.897854033280055, 118.77191762137305]</coor>
	</detector>
	<detector id="74">
		<volume>0.8</volume>
		<coor>[31.89818775697064, 118.77158275979265]</coor>
	</detector>
	<detector id="75">
		<volume>0.8</volume>
		<coor>[31.89852967091192, 118.77123967937797]</coor>
	</detector>
	<detector id="76">
		<volume>0.8</volume>
		<coor>[31.898871584853197, 118.77089659896328]</coor>
	</detector>
	<detector id="77">
		<volume>1.4</volume>
		<coor>[31.899213498794474, 118.77055351854858]</coor>
	</detector>
	<detector id="78">
		<volume>5.0</volume>
		<coor>[31.899555412735754, 118.7702104381339]</coor>
	</detector>
	<detector id="79">
		<volume>9.6</volume>
		<coor>[31.899868184853197, 118.76989659896327]</coor>
	</detector>
	<detector id="80">
		<volume>0.8</volume>
		<coor>[31.912334590248022, 118.77575373309307]</coor>
	</detector>
	<detector id="81">
		<volume>0.8</volume>
		<coor>[31.91225877074407, 118.77523219927917]</coor>
	</detector>
	<detector id="82">
		<volume>0.8</volume>
		<coor>[31.91218295124012, 118.77471066546528]</coor>
	</detector>
	<detector id="83">
		<volume>1.4</volume>
		<coor>[31.912107131736164, 118.7741891316514]</coor>
	</detector>
	<detector id="84">
		<volume>5.0</volume>
		<coor>[31.91203131223221, 118.77366759783752]</coor>
	</detector>
	<detector id="85">
		<volume>9.6</volume>
		<coor>[31.91195549272826, 118.77314606402362]</coor>
	</detector>
	<detector id="86">
		<volume>0.5</volume>
		<coor>[31.911879673224306, 118.77262453020973]</coor>
	</detector>
	<detector id="87">
		<volume>0.5</volume>
		<coor>[31.91180385372035, 118.77210299639586]</coor>
	</detector>
	<detector id="88">
		<volume>0.5</volume>
		<coor>[31.9117280342164, 118.77158146258196]</coor>
	</detector>
	<detector id="89">
		<volume>0.5</volume>
		<coor>[31.911652214712447, 118.77105992876807]</coor>
	</detector>
	<detector id="90">
		<volume>0.5</volume>
		<coor>[31.911576395208492, 118.77053839495419]</coor>
	</detector>
	<detector id="91">
		<volume>0.5</volume>
		<coor>[31.91150057570454, 118.7700168611403]</coor>
	</detector>
	<detector id="92">
		<volume>7.3</volume>
		<coor>[31.91142475620059, 118.76949532732641]</coor>
	</detector>
	<detector id="93">
		<volume>0.5</volume>
		<coor>[31.911348936696633, 118.76897379351252]</coor>
	</detector>
	<detector id="94">
		<volume>0.5</volume>
		<coor>[31.91127311719268, 118.76845225969865]</coor>
	</detector>
	<detector id="95">
		<volume>0.5</volume>
		<coor>[31.911197297688727, 118.76793072588475]</coor>
	</detector>
	<detector id="96">
		<volume>0.5</volume>
		<coor>[31.911121478184775, 118.76740919207086]</coor>
	</detector>
	<detector id="97">
		<volume>1.4</volume>
		<coor>[31.91104565868082, 118.76688765825698]</coor>
	</detector>
	<detector id="98">
		<volume>10.7</volume>
		<coor>[31.910969839176868, 118.7663661244431]</coor>
	</detector>
	<detector id="99">
		<volume>12.2</volume>
		<coor>[31.910894019672916, 118.7658445906292]</coor>
	</detector>
	<detector id="100">
		<volume>0.5</volume>
		<coor>[31.91081820016896, 118.7653230568153]</coor>
	</detector>
	<detector id="101">
		<volume>0.5</volume>
		<coor>[31.910742380665006, 118.76480152300144]</coor>
	</detector>
	<detector id="102">
		<volume>0.5</volume>
		<coor>[31.910672585456517, 118.76432142804725]</coor>
	</detector>
	<detector id="103">
		<volume>0.8</volume>
		<coor>[31.91061081505279, 118.76383989262386]</coor>
	</detector>
	<detector id="104">
		<volume>0.8</volume>
		<coor>[31.910551045158382, 118.76331547787159]</coor>
	</detector>
	<detector id="105">
		<volume>0.8</volume>
		<coor>[31.910491275263972, 118.76279106311931]</coor>
	</detector>
	<detector id="106">
		<volume>1.4</volume>
		<coor>[31.91043150536956, 118.76226664836702]</coor>
	</detector>
	<detector id="107">
		<volume>5.0</volume>
		<coor>[31.910371735475145, 118.76174223361474]</coor>
	</detector>
	<detector id="108">
		<volume>9.6</volume>
		<coor>[31.910311965580735, 118.76121781886246]</coor>
	</detector>
	<detector id="109">
		<volume>0.5</volume>
		<coor>[31.910252195686326, 118.76069340411019]</coor>
	</detector>
	<detector id="110">
		<volume>0.5</volume>
		<coor>[31.910192425791912, 118.76016898935791]</coor>
	</detector>
	<detector id="111">
		<volume>0.5</volume>
		<coor>[31.910142670422353, 118.75973244099089]</coor>
	</detector>
	<detector id="112">
		<volume>0.8</volume>
		<coor>[31.910086594047858, 118.7592970019758]</coor>
	</detector>
	<detector id="113">
		<volume>0.8</volume>
		<coor>[31.91001418214357, 118.7587748059274]</coor>
	</detector>
	<detector id="114">
		<volume>0.8</volume>
		<coor>[31.909941770239286, 118.75825260987898]</coor>
	</detector>
	<detector id="115">
		<volume>1.4</volume>
		<coor>[31.909869358335, 118.75773041383059]</coor>
	</detector>
	<detector id="116">
		<volume>5.0</volume>
		<coor>[31.909796946430713, 118.75720821778219]</coor>
	</detector>
	<detector id="117">
		<volume>9.6</volume>
		<coor>[31.90972453452643, 118.75668602173377]</coor>
	</detector>
	<detector id="118">
		<volume>0.5</volume>
		<coor>[31.90965212262214, 118.75616382568538]</coor>
	</detector>
	<detector id="119">
		<volume>0.5</volume>
		<coor>[31.909600758335, 118.75579341383059]</coor>
	</detector>
	<detector id="120">
		<volume>0.8</volume>
		<coor>[31.9048734753349, 118.77717202845854]</coor>
	</detector>
	<detector id="121">
		<volume>0.8</volume>
		<coor>[31.905318826004695, 118.77710328537563]</coor>
	</detector>
	<detector id="122">
		<volume>0.8</volume>
		<coor>[31.905764176674495, 118.77703454229271]</coor>
	</detector>
	<detector id="123">
		<volume>1.4</volume>
		<coor>[31.906209527344295, 118.77696579920979]</coor>
	</detector>
	<detector id="124">
		<volume>5.0</volume>
		<coor>[31.906654878014095, 118.77689705612688]</coor>
	</detector>
	<detector id="125">
		<volume>9.6</volume>
		<coor>[31.907100228683895, 118.77682831304398]</coor>
	</detector>
	<detector id="126">
		<volume>0.5</volume>
		<coor>[31.90754557935369, 118.77675956996106]</coor>
	</detector>
	<detector id="127">
		<volume>0.5</volume>
		<coor>[31.90799093002349, 118.77669082687814]</coor>
	</detector>
	<detector id="128">
		<volume>0.5</volume>
		<coor>[31.908436280693287, 118.77662208379523]</coor>
	</detector>
	<detector id="129">
		<volume>0.5</volume>
		<coor>[31.908881631363087, 118.77655334071233]</coor>
	</detector>
	<detector id="130">
		<volume>0.5</volume>
		<coor>[31.909326982032887, 118.7764845976294]</coor>
	</detector>
	<detector id="131">
		<volume>0.5</volume>
		<coor>[31.909772332702687, 118.77641585454649]</coor>
	</detector>
	<detector id="132">
		<volume>7.3</volume>
		<coor>[31.910217683372483, 118.77634711146358]</coor>
	</detector>
	<detector id="133">
		<volume>0.5</volume>
		<coor>[31.910663034042283, 118.77627836838067]</coor>
	</detector>
	<detector id="134">
		<volume>0.5</volume>
		<coor>[31.911108384712083, 118.77620962529775]</coor>
	</detector>
	<detector id="135">
		<volume>0.5</volume>
		<coor>[31.91155373538188, 118.77614088221483]</coor>
	</detector>
	<detector id="136">
		<volume>0.5</volume>
		<coor>[31.91199908605168, 118.77607213913193]</coor>
	</detector>
	<detector id="137">
		<volume>1.4</volume>
		<coor>[31.91229713069329, 118.77602613379523]</coor>
	</detector>
	<detector id="138">
		<volume>0.8</volume>
		<coor>[31.900214693895546, 118.76964546701286]</coor>
	</detector>
	<detector id="139">
		<volume>0.8</volume>
		<coor>[31.900624081686633, 118.76942780103857]</coor>
	</detector>
	<detector id="140">
		<volume>0.8</volume>
		<coor>[31.901033469477724, 118.7692101350643]</coor>
	</detector>
	<detector id="141">
		<volume>1.4</volume>
		<coor>[31.901442857268812, 118.76899246909002]</coor>
	</detector>
	<detector id="142">
		<volume>5.0</volume>
		<coor>[31.9018522450599, 118.76877480311575]</coor>
	</detector>
	<detector id="143">
		<volume>9.6</volume>
		<coor>[31.902261632850987, 118.76855713714146]</coor>
	</detector>
	<detector id="144">
		<volume>0.5</volume>
		<coor>[31.902671020642074, 118.76833947116717]</coor>
	</detector>
	<detector id="145">
		<volume>0.5</volume>
		<coor>[31.903080408433162, 118.76812180519289]</coor>
	</detector>
	<detector id="146">
		<volume>0.5</volume>
		<coor>[31.903489796224253, 118.76790413921862]</coor>
	</detector>
	<detector id="147">
		<volume>0.5</volume>
		<coor>[31.90389918401534, 118.76768647324434]</coor>
	</detector>
	<detector id="148">
		<volume>0.5</volume>
		<coor>[31.90430857180643, 118.76746880727005]</coor>
	</detector>
	<detector id="149">
		<volume>0.5</volume>
		<coor>[31.904717959597516, 118.76725114129577]</coor>
	</detector>
	<detector id="150">
		<volume>7.3</volume>
		<coor>[31.905127347388603, 118.76703347532148]</coor>
	</detector>
	<detector id="151">
		<volume>0.5</volume>
		<coor>[31.905536735179695, 118.76681580934721]</coor>
	</detector>
	<detector id="152">
		<volume>0.5</volume>
		<coor>[31.905946122970782, 118.76659814337293]</coor>
	</detector>
	<detector id="153">
		<volume>0.5</volume>
		<coor>[31.90635551076187, 118.76638047739864]</coor>
	</detector>
	<detector id="154">
		<volume>0.5</volume>
		<coor>[31.906764898552957, 118.76616281142437]</coor>
	</detector>
	<detector id="155">
		<volume>1.4</volume>
		<coor>[31.907174286344045, 118.76594514545008]</coor>
	</detector>
	<detector id="156">
		<volume>10.7</volume>
		<coor>[31.907583674135132, 118.7657274794758]</coor>
	</detector>
	<detector id="157">
		<volume>12.2</volume>
		<coor>[31.907993061926224, 118.76550981350152]</coor>
	</detector>
	<detector id="158">
		<volume>0.5</volume>
		<coor>[31.90840244971731, 118.76529214752725]</coor>
	</detector>
	<detector id="159">
		<volume>0.5</volume>
		<coor>[31.9088118375084, 118.76507448155296]</coor>
	</detector>
	<detector id="160">
		<volume>0.5</volume>
		<coor>[31.909221225299486, 118.76485681557868]</coor>
	</detector>
	<detector id="161">
		<volume>0.5</volume>
		<coor>[31.909630613090577, 118.76463914960439]</coor>
	</detector>
	<detector id="162">
		<volume>0.5</volume>
		<coor>[31.910040000881665, 118.76442148363012]</coor>
	</detector>
	<detector id="163">
		<volume>0.5</volume>
		<coor>[31.910442697388604, 118.76420737532149]</coor>
	</detector>
	<detector id="164">
		<volume>0.8</volume>
		<coor>[31.91654924926385, 118.7510621076051]</coor>
	</detector>
	<detector id="165">
		<volume>0.8</volume>
		<coor>[31.916151947791548, 118.7513089228153]</coor>
	</detector>
	<detector id="166">
		<volume>0.8</volume>
		<coor>[31.915754646319243, 118.7515557380255]</coor>
	</detector>
	<detector id="167">
		<volume>1.4</volume>
		<coor>[31.91535734484694, 118.75180255323568]</coor>
	</detector>
	<detector id="168">
		<volume>5.0</volume>
		<coor>[31.914960043374638, 118.75204936844588]</coor>
	</detector>
	<detector id="169">
		<volume>9.6</volume>
		<coor>[31.914562741902337, 118.75229618365609]</coor>
	</detector>
	<detector id="170">
		<volume>0.5</volume>
		<coor>[31.914165440430033, 118.75254299886628]</coor>
	</detector>
	<detector id="171">
		<volume>0.5</volume>
		<coor>[31.913768138957728, 118.75278981407646]</coor>
	</detector>
	<detector id="172">
		<volume>0.5</volume>
		<coor>[31.913370837485427, 118.75303662928667]</coor>
	</detector>
	<detector id="173">
		<volume>0.5</volume>
		<coor>[31.912973536013126, 118.75328344449686]</coor>
	</detector>
	<detector id="174">
		<volume>0.5</volume>
		<coor>[31.912576234540822, 118.75353025970705]</coor>
	</detector>
	<detector id="175">
		<volume>0.5</volume>
		<coor>[31.912178933068517, 118.75377707491725]</coor>
	</detector>
	<detector id="176">
		<volume>7.3</volume>
		<coor>[31.911781631596217, 118.75402389012744]</coor>
	</detector>
	<detector id="177">
		<volume>0.5</volume>
		<coor>[31.911384330123916, 118.75427070533763]</coor>
	</detector>
	<detector id="178">
		<volume>0.5</volume>
		<coor>[31.91098702865161, 118.75451752054784]</coor>
	</detector>
	<detector id="179">
		<volume>0.5</volume>
		<coor>[31.910589727179307, 118.75476433575803]</coor>
	</detector>
	<detector id="180">
		<volume>0.5</volume>
		<coor>[31.910192425707006, 118.75501115096822]</coor>
	</detector>
	<detector id="181">
		<volume>1.4</volume>
		<coor>[31.909795124234705, 118.75525796617842]</coor>
	</detector>
	<detector id="182">
		<volume>10.7</volume>
		<coor>[31.909544136749275, 118.75541388689176]</coor>
	</detector>
	<detector id="183">
		<volume>0.8</volume>
		<coor>[31.887321285611883, 118.76450902079071]</coor>
	</detector>
	<detector id="184">
		<volume>0.8</volume>
		<coor>[31.88774765683565, 118.76434266237217]</coor>
	</detector>
	<detector id="185">
		<volume>0.8</volume>
		<coor>[31.88817402805942, 118.7641763039536]</coor>
	</detector>
	<detector id="186">
		<volume>1.4</volume>
		<coor>[31.88860039928319, 118.76400994553507]</coor>
	</detector>
	<detector id="187">
		<volume>5.0</volume>
		<coor>[31.88902677050696, 118.7638435871165]</coor>
	</detector>
	<detector id="188">
		<volume>9.6</volume>
		<coor>[31.889453141730726, 118.76367722869796]</coor>
	</detector>
	<detector id="189">
		<volume>0.5</volume>
		<coor>[31.889879512954497, 118.76351087027939]</coor>
	</detector>
	<detector id="190">
		<volume>0.5</volume>
		<coor>[31.890305884178268, 118.76334451186085]</coor>
	</detector>
	<detector id="191">
		<volume>0.5</volume>
		<coor>[31.890732255402035, 118.76317815344228]</coor>
	</detector>
	<detector id="192">
		<volume>0.5</volume>
		<coor>[31.891158626625803, 118.76301179502371]</coor>
	</detector>
	<detector id="193">
		<volume>0.5</volume>
		<coor>[31.891584997849574, 118.76284543660518]</coor>
	</detector>
	<detector id="194">
		<volume>0.5</volume>
		<coor>[31.892011369073344, 118.76267907818661]</coor>
	</detector>
	<detector id="195">
		<volume>7.3</volume>
		<coor>[31.89243774029711, 118.76251271976807]</coor>
	</detector>
	<detector id="196">
		<volume>0.5</volume>
		<coor>[31.89286411152088, 118.7623463613495]</coor>
	</detector>
	<detector id="197">
		<volume>0.5</volume>
		<coor>[31.89329048274465, 118.76218000293096]</coor>
	</detector>
	<detector id="198">
		<volume>0.5</volume>
		<coor>[31.89371685396842, 118.7620136445124]</coor>
	</detector>
	<detector id="199">
		<volume>0.5</volume>
		<coor>[31.894143225192188, 118.76184728609385]</coor>
	</detector>
	<detector id="200">
		<volume>1.4</volume>
		<coor>[31.894569596415955, 118.76168092767529]</coor>
	</detector>
	<detector id="201">
		<volume>10.7</volume>
		<coor>[31.894995967639726, 118.76151456925675]</coor>
	</detector>
	<detector id="202">
		<volume>12.2</volume>
		<coor>[31.895422338863497, 118.76134821083818]</coor>
	</detector>
	<detector id="203">
		<volume>0.5</volume>
		<coor>[31.895848710087265, 118.76118185241964]</coor>
	</detector>
	<detector id="204">
		<volume>0.5</volume>
		<coor>[31.896275081311032, 118.76101549400107]</coor>
	</detector>
	<detector id="205">
		<volume>0.5</volume>
		<coor>[31.896701452534803, 118.76084913558253]</coor>
	</detector>
	<detector id="206">
		<volume>0.5</volume>
		<coor>[31.897127823758574, 118.76068277716396]</coor>
	</detector>
	<detector id="207">
		<volume>0.5</volume>
		<coor>[31.89755419498234, 118.76051641874542]</coor>
	</detector>
	<detector id="208">
		<volume>0.5</volume>
		<coor>[31.897851240297115, 118.76040051976807]</coor>
	</detector>
	<detector id="209">
		<volume>0.8</volume>
		<coor>[31.898147641587318, 118.76028235465151]</coor>
	</detector>
	<detector id="210">
		<volume>0.8</volume>
		<coor>[31.898572724761955, 118.76011146395454]</coor>
	</detector>
	<detector id="211">
		<volume>0.8</volume>
		<coor>[31.89899780793659, 118.75994057325758]</coor>
	</detector>
	<detector id="212">
		<volume>1.4</volume>
		<coor>[31.89942289111122, 118.7597696825606]</coor>
	</detector>
	<detector id="213">
		<volume>5.0</volume>
		<coor>[31.89984797428586, 118.75959879186364]</coor>
	</detector>
	<detector id="214">
		<volume>9.6</volume>
		<coor>[31.900273057460492, 118.75942790116667]</coor>
	</detector>
	<detector id="215">
		<volume>0.5</volume>
		<coor>[31.90069814063513, 118.7592570104697]</coor>
	</detector>
	<detector id="216">
		<volume>0.5</volume>
		<coor>[31.901123223809762, 118.75908611977273]</coor>
	</detector>
	<detector id="217">
		<volume>0.5</volume>
		<coor>[31.901548306984395, 118.75891522907577]</coor>
	</detector>
	<detector id="218">
		<volume>0.5</volume>
		<coor>[31.90197339015903, 118.75874433837879]</coor>
	</detector>
	<detector id="219">
		<volume>0.5</volume>
		<coor>[31.902398473333665, 118.75857344768181]</coor>
	</detector>
	<detector id="220">
		<volume>0.5</volume>
		<coor>[31.902823556508302, 118.75840255698486]</coor>
	</detector>
	<detector id="221">
		<volume>7.3</volume>
		<coor>[31.903248639682936, 118.75823166628788]</coor>
	</detector>
	<detector id="222">
		<volume>0.5</volume>
		<coor>[31.90367372285757, 118.7580607755909]</coor>
	</detector>
	<detector id="223">
		<volume>0.5</volume>
		<coor>[31.904098806032202, 118.75788988489396]</coor>
	</detector>
	<detector id="224">
		<volume>0.5</volume>
		<coor>[31.90452388920684, 118.75771899419698]</coor>
	</detector>
	<detector id="225">
		<volume>0.5</volume>
		<coor>[31.904948972381476, 118.7575481035]</coor>
	</detector>
	<detector id="226">
		<volume>1.4</volume>
		<coor>[31.90537405555611, 118.75737721280305]</coor>
	</detector>
	<detector id="227">
		<volume>10.7</volume>
		<coor>[31.905799138730742, 118.75720632210607]</coor>
	</detector>
	<detector id="228">
		<volume>12.2</volume>
		<coor>[31.906224221905376, 118.7570354314091]</coor>
	</detector>
	<detector id="229">
		<volume>0.5</volume>
		<coor>[31.906649305080013, 118.75686454071214]</coor>
	</detector>
	<detector id="230">
		<volume>0.5</volume>
		<coor>[31.90707438825465, 118.75669365001517]</coor>
	</detector>
	<detector id="231">
		<volume>0.5</volume>
		<coor>[31.907499471429283, 118.75652275931819]</coor>
	</detector>
	<detector id="232">
		<volume>0.5</volume>
		<coor>[31.907924554603916, 118.75635186862124]</coor>
	</detector>
	<detector id="233">
		<volume>0.5</volume>
		<coor>[31.90834963777855, 118.75618097792426]</coor>
	</detector>
	<detector id="234">
		<volume>0.5</volume>
		<coor>[31.908774720953186, 118.75601008722728]</coor>
	</detector>
	<detector id="235">
		<volume>0.5</volume>
		<coor>[31.90919980412782, 118.75583919653032]</coor>
	</detector>
	<detector id="236">
		<volume>0.5</volume>
		<coor>[31.90949897285757, 118.75571892559091]</coor>
	</detector>
	<detector id="237">
		<volume>0.8</volume>
		<coor>[31.88843361943457, 118.76727088073139]</coor>
	</detector>
	<detector id="238">
		<volume>0.8</volume>
		<coor>[31.888207458303704, 118.76681384219418]</coor>
	</detector>
	<detector id="239">
		<volume>0.8</volume>
		<coor>[31.887981297172843, 118.76635680365695]</coor>
	</detector>
	<detector id="240">
		<volume>1.4</volume>
		<coor>[31.88775513604198, 118.76589976511974]</coor>
	</detector>
	<detector id="241">
		<volume>5.0</volume>
		<coor>[31.887528974911117, 118.7654427265825]</coor>
	</detector>
	<detector id="242">
		<volume>9.6</volume>
		<coor>[31.887302813780252, 118.7649856880453]</coor>
	</detector>
	<detector id="243">
		<volume>0.5</volume>
		<coor>[31.88714891660741, 118.76467468438834]</coor>
	</detector>
	<detector id="244">
		<volume>0.8</volume>
		<coor>[31.892857367744856, 118.77169998646002]</coor>
	</detector>
	<detector id="245">
		<volume>0.8</volume>
		<coor>[31.892511303234564, 118.77136275938008]</coor>
	</detector>
	<detector id="246">
		<volume>0.8</volume>
		<coor>[31.892165238724274, 118.77102553230014]</coor>
	</detector>
	<detector id="247">
		<volume>1.4</volume>
		<coor>[31.891819174213985, 118.77068830522019]</coor>
	</detector>
	<detector id="248">
		<volume>5.0</volume>
		<coor>[31.891473109703693, 118.77035107814024]</coor>
	</detector>
	<detector id="249">
		<volume>9.6</volume>
		<coor>[31.8911270451934, 118.7700138510603]</coor>
	</detector>
	<detector id="250">
		<volume>0.5</volume>
		<coor>[31.89078098068311, 118.76967662398035]</coor>
	</detector>
	<detector id="251">
		<volume>0.5</volume>
		<coor>[31.890434916172822, 118.76933939690039]</coor>
	</detector>
	<detector id="252">
		<volume>0.5</volume>
		<coor>[31.89008885166253, 118.76900216982045]</coor>
	</detector>
	<detector id="253">
		<volume>0.5</volume>
		<coor>[31.889742787152237, 118.7686649427405]</coor>
	</detector>
	<detector id="254">
		<volume>0.5</volume>
		<coor>[31.889396722641948, 118.76832771566055]</coor>
	</detector>
	<detector id="255">
		<volume>0.5</volume>
		<coor>[31.88905065813166, 118.76799048858061]</coor>
	</detector>
	<detector id="256">
		<volume>7.3</volume>
		<coor>[31.888712162938255, 118.76766063752032]</coor>
	</detector>
	<detector id="257">
		<volume>0.8</volume>
		<coor>[31.89545917513736, 118.77398221331414]</coor>
	</detector>
	<detector id="258">
		<volume>0.8</volume>
		<coor>[31.895097925412088, 118.77366783994242]</coor>
	</detector>
	<detector id="259">
		<volume>0.8</volume>
		<coor>[31.89473667568681, 118.77335346657071]</coor>
	</detector>
	<detector id="260">
		<volume>1.4</volume>
		<coor>[31.894375425961535, 118.773039093199]</coor>
	</detector>
	<detector id="261">
		<volume>5.0</volume>
		<coor>[31.89401417623626, 118.77272471982728]</coor>
	</detector>
	<detector id="262">
		<volume>9.6</volume>
		<coor>[31.89365292651098, 118.77241034645556]</coor>
	</detector>
	<detector id="263">
		<volume>0.5</volume>
		<coor>[31.893291676785708, 118.77209597308385]</coor>
	</detector>
	<detector id="264">
		<volume>0.5</volume>
		<coor>[31.893070725961536, 118.771903693199]</coor>
	</detector>
	<detector id="265">
		<volume>0.8</volume>
		<coor>[31.895830849013535, 118.7742784485637]</coor>
	</detector>
	<detector id="266">
		<volume>0.8</volume>
		<coor>[31.896212947040603, 118.77455654569115]</coor>
	</detector>
	<detector id="267">
		<volume>0.8</volume>
		<coor>[31.896595045067667, 118.7748346428186]</coor>
	</detector>
	<detector id="268">
		<volume>1.4</volume>
		<coor>[31.89697714309473, 118.77511273994604]</coor>
	</detector>
	<detector id="269">
		<volume>5.0</volume>
		<coor>[31.897359241121798, 118.77539083707347]</coor>
	</detector>
	<detector id="270">
		<volume>9.6</volume>
		<coor>[31.897741339148865, 118.77566893420092]</coor>
	</detector>
	<detector id="271">
		<volume>0.5</volume>
		<coor>[31.89812343717593, 118.77594703132836]</coor>
	</detector>
	<detector id="272">
		<volume>0.5</volume>
		<coor>[31.898505535202993, 118.77622512845579]</coor>
	</detector>
	<detector id="273">
		<volume>0.5</volume>
		<coor>[31.89888763323006, 118.77650322558324]</coor>
	</detector>
	<detector id="274">
		<volume>0.5</volume>
		<coor>[31.899269731257128, 118.77678132271068]</coor>
	</detector>
	<detector id="275">
		<volume>0.5</volume>
		<coor>[31.899651829284192, 118.77705941983811]</coor>
	</detector>
	<detector id="276">
		<volume>0.5</volume>
		<coor>[31.900033927311256, 118.77733751696556]</coor>
	</detector>
	<detector id="277">
		<volume>7.3</volume>
		<coor>[31.900416025338323, 118.77761561409301]</coor>
	</detector>
	<detector id="278">
		<volume>0.5</volume>
		<coor>[31.900830180097543, 118.7777244131889]</coor>
	</detector>
	<detector id="279">
		<volume>0.5</volume>
		<coor>[31.901276391588922, 118.77766391425325]</coor>
	</detector>
	<detector id="280">
		<volume>0.5</volume>
		<coor>[31.901722603080295, 118.77760341531763]</coor>
	</detector>
	<detector id="281">
		<volume>0.5</volume>
		<coor>[31.902168814571674, 118.77754291638198]</coor>
	</detector>
	<detector id="282">
		<volume>1.4</volume>
		<coor>[31.902615026063046, 118.77748241744635]</coor>
	</detector>
	<detector id="283">
		<volume>10.7</volume>
		<coor>[31.903061237554425, 118.77742191851073]</coor>
	</detector>
	<detector id="284">
		<volume>12.2</volume>
		<coor>[31.903507449045804, 118.77736141957507]</coor>
	</detector>
	<detector id="285">
		<volume>0.5</volume>
		<coor>[31.903953660537177, 118.77730092063945]</coor>
	</detector>
	<detector id="286">
		<volume>0.5</volume>
		<coor>[31.904413783141433, 118.77723853558581]</coor>
	</detector>
	<detector id="287">
		<volume>0.8</volume>
		<coor>[31.898598856359328, 118.76661586669778]</coor>
	</detector>
	<detector id="288">
		<volume>0.8</volume>
		<coor>[31.898997369077975, 118.76637180009331]</coor>
	</detector>
	<detector id="289">
		<volume>0.8</volume>
		<coor>[31.89939588179663, 118.76612773348884]</coor>
	</detector>
	<detector id="290">
		<volume>1.4</volume>
		<coor>[31.89979439451528, 118.7658836668844]</coor>
	</detector>
	<detector id="291">
		<volume>5.0</volume>
		<coor>[31.90019290723393, 118.76563960027994]</coor>
	</detector>
	<detector id="292">
		<volume>9.6</volume>
		<coor>[31.900591419952583, 118.76539553367547]</coor>
	</detector>
	<detector id="293">
		<volume>0.5</volume>
		<coor>[31.90098993267123, 118.76515146707104]</coor>
	</detector>
	<detector id="294">
		<volume>0.5</volume>
		<coor>[31.901388445389884, 118.76490740046657]</coor>
	</detector>
	<detector id="295">
		<volume>0.5</volume>
		<coor>[31.90178695810853, 118.7646633338621]</coor>
	</detector>
	<detector id="296">
		<volume>0.5</volume>
		<coor>[31.902185470827185, 118.76441926725767]</coor>
	</detector>
	<detector id="297">
		<volume>0.5</volume>
		<coor>[31.90258398354584, 118.7641752006532]</coor>
	</detector>
	<detector id="298">
		<volume>0.5</volume>
		<coor>[31.902982496264485, 118.76393113404875]</coor>
	</detector>
	<detector id="299">
		<volume>7.3</volume>
		<coor>[31.90338100898314, 118.7636870674443]</coor>
	</detector>
	<detector id="300">
		<volume>0.5</volume>
		<coor>[31.903779521701786, 118.76344300083983]</coor>
	</detector>
	<detector id="301">
		<volume>0.5</volume>
		<coor>[31.90417803442044, 118.76319893423538]</coor>
	</detector>
	<detector id="302">
		<volume>0.5</volume>
		<coor>[31.90457654713909, 118.76295486763092]</coor>
	</detector>
	<detector id="303">
		<volume>0.5</volume>
		<coor>[31.90497505985774, 118.76271080102646]</coor>
	</detector>
	<detector id="304">
		<volume>1.4</volume>
		<coor>[31.905373572576394, 118.762466734422]</coor>
	</detector>
	<detector id="305">
		<volume>10.7</volume>
		<coor>[31.90577208529504, 118.76222266781755]</coor>
	</detector>
	<detector id="306">
		<volume>12.2</volume>
		<coor>[31.906170598013695, 118.76197860121309]</coor>
	</detector>
	<detector id="307">
		<volume>0.5</volume>
		<coor>[31.90656911073234, 118.76173453460864]</coor>
	</detector>
	<detector id="308">
		<volume>0.5</volume>
		<coor>[31.906967623450996, 118.76149046800418]</coor>
	</detector>
	<detector id="309">
		<volume>0.5</volume>
		<coor>[31.90736613616965, 118.76124640139972]</coor>
	</detector>
	<detector id="310">
		<volume>0.5</volume>
		<coor>[31.907764648888296, 118.76100233479526]</coor>
	</detector>
	<detector id="311">
		<volume>0.5</volume>
		<coor>[31.90816316160695, 118.76075826819081]</coor>
	</detector>
	<detector id="312">
		<volume>0.5</volume>
		<coor>[31.908561674325597, 118.76051420158635]</coor>
	</detector>
	<detector id="313">
		<volume>0.5</volume>
		<coor>[31.90896018704425, 118.7602701349819]</coor>
	</detector>
	<detector id="314">
		<volume>0.5</volume>
		<coor>[31.9093586997629, 118.76002606837744]</coor>
	</detector>
	<detector id="315">
		<volume>0.5</volume>
		<coor>[31.90975721248155, 118.75978200177298]</coor>
	</detector>
	<detector id="316">
		<volume>0.5</volume>
		<coor>[31.91003963442044, 118.75960903423538]</coor>
	</detector>
	<detector id="317">
		<volume>0.8</volume>
		<coor>[31.896382397275282, 118.76871309877738]</coor>
	</detector>
	<detector id="318">
		<volume>0.8</volume>
		<coor>[31.89672779182585, 118.76837489633218]</coor>
	</detector>
	<detector id="319">
		<volume>0.8</volume>
		<coor>[31.897073186376417, 118.76803669388696]</coor>
	</detector>
	<detector id="320">
		<volume>1.4</volume>
		<coor>[31.89741858092698, 118.76769849144173]</coor>
	</detector>
	<detector id="321">
		<volume>5.0</volume>
		<coor>[31.897763975477545, 118.76736028899653]</coor>
	</detector>
	<detector id="322">
		<volume>9.6</volume>
		<coor>[31.898109370028113, 118.76702208655131]</coor>
	</detector>
	<detector id="323">
		<volume>0.5</volume>
		<coor>[31.898340833651698, 118.76679544266435]</coor>
	</detector>
	<detector id="324">
		<volume>0.8</volume>
		<coor>[31.893205993543376, 118.77170309351058]</coor>
	</detector>
	<detector id="325">
		<volume>0.8</volume>
		<coor>[31.89355718063012, 118.77137328053175]</coor>
	</detector>
	<detector id="326">
		<volume>0.8</volume>
		<coor>[31.89390836771686, 118.77104346755291]</coor>
	</detector>
	<detector id="327">
		<volume>1.4</volume>
		<coor>[31.89425955480361, 118.77071365457408]</coor>
	</detector>
	<detector id="328">
		<volume>5.0</volume>
		<coor>[31.894610741890354, 118.77038384159525]</coor>
	</detector>
	<detector id="329">
		<volume>9.6</volume>
		<coor>[31.8949619289771, 118.77005402861641]</coor>
	</detector>
	<detector id="330">
		<volume>0.5</volume>
		<coor>[31.895313116063846, 118.76972421563758]</coor>
	</detector>
	<detector id="331">
		<volume>0.5</volume>
		<coor>[31.89566430315059, 118.76939440265875]</coor>
	</detector>
	<detector id="332">
		<volume>0.5</volume>
		<coor>[31.89601549023734, 118.76906458967991]</coor>
	</detector>
	<detector id="333">
		<volume>0.5</volume>
		<coor>[31.896200391890353, 118.76889094159525]</coor>
	</detector>
	<detector id="334">
		<volume>0.8</volume>
		<coor>[31.89390547177097, 118.76485816666548]</coor>
	</detector>
	<detector id="335">
		<volume>0.8</volume>
		<coor>[31.89433281531292, 118.76469529999643]</coor>
	</detector>
	<detector id="336">
		<volume>0.8</volume>
		<coor>[31.894760158854865, 118.76453243332739]</coor>
	</detector>
	<detector id="337">
		<volume>1.4</volume>
		<coor>[31.89518750239681, 118.76436956665833]</coor>
	</detector>
	<detector id="338">
		<volume>5.0</volume>
		<coor>[31.89561484593876, 118.76420669998927]</coor>
	</detector>
	<detector id="339">
		<volume>9.6</volume>
		<coor>[31.896042189480703, 118.76404383332023]</coor>
	</detector>
	<detector id="340">
		<volume>0.5</volume>
		<coor>[31.89646953302265, 118.76388096665119]</coor>
	</detector>
	<detector id="341">
		<volume>0.5</volume>
		<coor>[31.896896876564597, 118.76371809998213]</coor>
	</detector>
	<detector id="342">
		<volume>0.5</volume>
		<coor>[31.89732422010654, 118.76355523331307]</coor>
	</detector>
	<detector id="343">
		<volume>0.5</volume>
		<coor>[31.89775156364849, 118.76339236664404]</coor>
	</detector>
	<detector id="344">
		<volume>0.5</volume>
		<coor>[31.898006867709732, 118.76329506665476]</coor>
	</detector>
	<detector id="345">
		<volume>0.8</volume>
		<coor>[31.888753578270638, 118.76739647352682]</coor>
	</detector>
	<detector id="346">
		<volume>0.8</volume>
		<coor>[31.889167334811916, 118.76719062058046]</coor>
	</detector>
	<detector id="347">
		<volume>0.8</volume>
		<coor>[31.889581091353193, 118.76698476763409]</coor>
	</detector>
	<detector id="348">
		<volume>1.4</volume>
		<coor>[31.889994847894467, 118.7667789146877]</coor>
	</detector>
	<detector id="349">
		<volume>5.0</volume>
		<coor>[31.890408604435745, 118.76657306174135]</coor>
	</detector>
	<detector id="350">
		<volume>9.6</volume>
		<coor>[31.890822360977022, 118.76636720879497]</coor>
	</detector>
	<detector id="351">
		<volume>0.5</volume>
		<coor>[31.8912361175183, 118.76616135584861]</coor>
	</detector>
	<detector id="352">
		<volume>0.5</volume>
		<coor>[31.891649874059578, 118.76595550290224]</coor>
	</detector>
	<detector id="353">
		<volume>0.5</volume>
		<coor>[31.892063630600852, 118.76574964995586]</coor>
	</detector>
	<detector id="354">
		<volume>0.5</volume>
		<coor>[31.89247738714213, 118.76554379700951]</coor>
	</detector>
	<detector id="355">
		<volume>0.5</volume>
		<coor>[31.892891143683407, 118.76533794406313]</coor>
	</detector>
	<detector id="356">
		<volume>0.5</volume>
		<coor>[31.893304900224685, 118.76513209111675]</coor>
	</detector>
	<detector id="357">
		<volume>7.3</volume>
		<coor>[31.89360178924766, 118.76498438232179]</coor>
	</detector>
	<detector id="358">
		<volume>0.8</volume>
		<coor>[31.897883082847372, 118.7715417777079]</coor>
	</detector>
	<detector id="359">
		<volume>0.8</volume>
		<coor>[31.89761564854212, 118.77111673312369]</coor>
	</detector>
	<detector id="360">
		<volume>0.8</volume>
		<coor>[31.897348214236864, 118.77069168853949]</coor>
	</detector>
	<detector id="361">
		<volume>1.4</volume>
		<coor>[31.897080779931613, 118.77026664395527]</coor>
	</detector>
	<detector id="362">
		<volume>5.0</volume>
		<coor>[31.896813345626363, 118.76984159937106]</coor>
	</detector>
	<detector id="363">
		<volume>9.6</volume>
		<coor>[31.896545911321105, 118.76941655478686]</coor>
	</detector>
	<detector id="364">
		<volume>0.5</volume>
		<coor>[31.89631094708424, 118.76904311624737]</coor>
	</detector>
	<detector id="365">
		<volume>0.8</volume>
		<coor>[31.896074712189396, 118.76867080004973]</coor>
	</detector>
	<detector id="366">
		<volume>0.8</volume>
		<coor>[31.89580473656818, 118.76824800014919]</coor>
	</detector>
	<detector id="367">
		<volume>0.8</volume>
		<coor>[31.895534760946965, 118.76782520024864]</coor>
	</detector>
	<detector id="368">
		<volume>1.4</volume>
		<coor>[31.895264785325754, 118.76740240034812]</coor>
	</detector>
	<detector id="369">
		<volume>5.0</volume>
		<coor>[31.894994809704542, 118.76697960044757]</coor>
	</detector>
	<detector id="370">
		<volume>9.6</volume>
		<coor>[31.894724834083327, 118.76655680054702]</coor>
	</detector>
	<detector id="371">
		<volume>0.5</volume>
		<coor>[31.89445485846211, 118.7661340006465]</coor>
	</detector>
	<detector id="372">
		<volume>0.5</volume>
		<coor>[31.894184882840904, 118.76571120074595]</coor>
	</detector>
	<detector id="373">
		<volume>0.5</volume>
		<coor>[31.89391490721969, 118.7652884008454]</coor>
	</detector>
	<detector id="374">
		<volume>0.5</volume>
		<coor>[31.89373585970454, 118.76500800044758]</coor>
	</detector>
	<detector id="375">
		<volume>0.8</volume>
		<coor>[31.88032457882103, 118.7645922]</coor>
	</detector>
	<detector id="376">
		<volume>0.8</volume>
		<coor>[31.880773736463087, 118.7645922]</coor>
	</detector>
	<detector id="377">
		<volume>0.8</volume>
		<coor>[31.881222894105147, 118.7645922]</coor>
	</detector>
	<detector id="378">
		<volume>1.4</volume>
		<coor>[31.881672051747206, 118.7645922]</coor>
	</detector>
	<detector id="379">
		<volume>5.0</volume>
		<coor>[31.882121209389265, 118.7645922]</coor>
	</detector>
	<detector id="380">
		<volume>9.6</volume>
		<coor>[31.882570367031327, 118.7645922]</coor>
	</detector>
	<detector id="381">
		<volume>0.5</volume>
		<coor>[31.883019524673387, 118.7645922]</coor>
	</detector>
	<detector id="382">
		<volume>0.5</volume>
		<coor>[31.883468682315446, 118.7645922]</coor>
	</detector>
	<detector id="383">
		<volume>0.5</volume>
		<coor>[31.883917839957505, 118.7645922]</coor>
	</detector>
	<detector id="384">
		<volume>0.5</volume>
		<coor>[31.884366997599564, 118.7645922]</coor>
	</detector>
	<detector id="385">
		<volume>0.5</volume>
		<coor>[31.884816155241623, 118.7645922]</coor>
	</detector>
	<detector id="386">
		<volume>0.5</volume>
		<coor>[31.885265312883682, 118.7645922]</coor>
	</detector>
	<detector id="387">
		<volume>7.3</volume>
		<coor>[31.88571447052574, 118.7645922]</coor>
	</detector>
	<detector id="388">
		<volume>0.5</volume>
		<coor>[31.8861636281678, 118.7645922]</coor>
	</detector>
	<detector id="389">
		<volume>0.5</volume>
		<coor>[31.88661278580986, 118.7645922]</coor>
	</detector>
	<detector id="390">
		<volume>0.5</volume>
		<coor>[31.886972732315442, 118.7645922]</coor>
	</detector>
	<detector id="391">
		<volume>0.8</volume>
		<coor>[31.905536826865475, 118.77897845373096]</coor>
	</detector>
	<detector id="392">
		<volume>0.8</volume>
		<coor>[31.905308880596426, 118.77852256119286]</coor>
	</detector>
	<detector id="393">
		<volume>0.8</volume>
		<coor>[31.905080934327376, 118.77806666865476]</coor>
	</detector>
	<detector id="394">
		<volume>1.4</volume>
		<coor>[31.904852988058323, 118.77761077611665]</coor>
	</detector>
	<detector id="395">
		<volume>5.0</volume>
		<coor>[31.9046949074619, 118.77729461492379]</coor>
	</detector>
	<detector id="396">
		<volume>0.8</volume>
		<coor>[31.913335228786977, 118.78275360150883]</coor>
	</detector>
	<detector id="397">
		<volume>0.8</volume>
		<coor>[31.91326068636093, 118.7822318045265]</coor>
	</detector>
	<detector id="398">
		<volume>0.8</volume>
		<coor>[31.913186143934883, 118.78171000754416]</coor>
	</detector>
	<detector id="399">
		<volume>1.4</volume>
		<coor>[31.913111601508835, 118.78118821056182]</coor>
	</detector>
	<detector id="400">
		<volume>5.0</volume>
		<coor>[31.913037059082786, 118.7806664135795]</coor>
	</detector>
	<detector id="401">
		<volume>9.6</volume>
		<coor>[31.91296251665674, 118.78014461659717]</coor>
	</detector>
	<detector id="402">
		<volume>0.5</volume>
		<coor>[31.912887974230692, 118.77962281961483]</coor>
	</detector>
	<detector id="403">
		<volume>0.5</volume>
		<coor>[31.912813431804643, 118.77910102263249]</coor>
	</detector>
	<detector id="404">
		<volume>0.5</volume>
		<coor>[31.912738889378595, 118.77857922565016]</coor>
	</detector>
	<detector id="405">
		<volume>0.5</volume>
		<coor>[31.912664346952546, 118.77805742866784]</coor>
	</detector>
	<detector id="406">
		<volume>0.5</volume>
		<coor>[31.9125898045265, 118.7775356316855]</coor>
	</detector>
	<detector id="407">
		<volume>0.5</volume>
		<coor>[31.912515262100452, 118.77701383470315]</coor>
	</detector>
	<detector id="408">
		<volume>7.3</volume>
		<coor>[31.912440719674404, 118.77649203772083]</coor>
	</detector>
	<detector id="409">
		<volume>0.5</volume>
		<coor>[31.91238797423069, 118.77612281961484]</coor>
	</detector>
	<detector id="410">
		<volume>0.8</volume>
		<coor>[31.91514792117897, 118.7760145]</coor>
	</detector>
	<detector id="411">
		<volume>0.8</volume>
		<coor>[31.91469876353691, 118.7760145]</coor>
	</detector>
	<detector id="412">
		<volume>0.8</volume>
		<coor>[31.914249605894852, 118.7760145]</coor>
	</detector>
	<detector id="413">
		<volume>1.4</volume>
		<coor>[31.913800448252793, 118.7760145]</coor>
	</detector>
	<detector id="414">
		<volume>5.0</volume>
		<coor>[31.913351290610734, 118.7760145]</coor>
	</detector>
	<detector id="415">
		<volume>9.6</volume>
		<coor>[31.912902132968675, 118.7760145]</coor>
	</detector>
	<detector id="416">
		<volume>0.5</volume>
		<coor>[31.912525027073823, 118.7760145]</coor>
	</detector>
	<detector id="417">
		<volume>0.8</volume>
		<coor>[31.897945392496197, 118.76063204667926]</coor>
	</detector>
	<detector id="418">
		<volume>0.8</volume>
		<coor>[31.897965977488596, 118.76116054003782]</coor>
	</detector>
	<detector id="419">
		<volume>0.8</volume>
		<coor>[31.897986562480988, 118.76168903339638]</coor>
	</detector>
	<detector id="420">
		<volume>1.4</volume>
		<coor>[31.898007147473386, 118.76221752675492]</coor>
	</detector>
	<detector id="421">
		<volume>5.0</volume>
		<coor>[31.898027732465778, 118.76274602011347]</coor>
	</detector>
	<detector id="422">
		<volume>9.6</volume>
		<coor>[31.89804326248099, 118.76314473339637]</coor>
	</detector>
	<detector id="423">
		<volume>0.8</volume>
		<coor>[31.898075162610166, 118.7635418544283]</coor>
	</detector>
	<detector id="424">
		<volume>0.8</volume>
		<coor>[31.898128487830494, 118.76406716328488]</coor>
	</detector>
	<detector id="425">
		<volume>0.8</volume>
		<coor>[31.898181813050822, 118.76459247214146]</coor>
	</detector>
	<detector id="426">
		<volume>1.4</volume>
		<coor>[31.898235138271147, 118.76511778099805]</coor>
	</detector>
	<detector id="427">
		<volume>5.0</volume>
		<coor>[31.898288463491475, 118.76564308985465]</coor>
	</detector>
	<detector id="428">
		<volume>9.6</volume>
		<coor>[31.898341788711804, 118.76616839871122]</coor>
	</detector>
	<detector id="429">
		<volume>0.5</volume>
		<coor>[31.898384025660985, 118.76658447656976]</coor>
	</detector>
	<detector id="430">
		<volume>0.8</volume>
		<coor>[31.898519152576128, 118.766961830943]</coor>
	</detector>
	<detector id="431">
		<volume>0.8</volume>
		<coor>[31.898758257728375, 118.76740969282903]</coor>
	</detector>
	<detector id="432">
		<volume>0.8</volume>
		<coor>[31.89899736288063, 118.76785755471505]</coor>
	</detector>
	<detector id="433">
		<volume>1.4</volume>
		<coor>[31.899236468032882, 118.76830541660107]</coor>
	</detector>
	<detector id="434">
		<volume>5.0</volume>
		<coor>[31.89947557318513, 118.7687532784871]</coor>
	</detector>
	<detector id="435">
		<volume>9.6</volume>
		<coor>[31.899714678337382, 118.76920114037313]</coor>
	</detector>
	<detector id="436">
		<volume>0.5</volume>
		<coor>[31.899922115456754, 118.76958968565808]</coor>
	</detector>
	<detector id="437">
		<volume>0.8</volume>
		<coor>[31.90014283371343, 118.7699676016109]</coor>
	</detector>
	<detector id="438">
		<volume>0.8</volume>
		<coor>[31.900408501140298, 118.7703942048327]</coor>
	</detector>
	<detector id="439">
		<volume>0.8</volume>
		<coor>[31.900674168567157, 118.7708208080545]</coor>
	</detector>
	<detector id="440">
		<volume>1.4</volume>
		<coor>[31.90093983599402, 118.77124741127629]</coor>
	</detector>
	<detector id="441">
		<volume>5.0</volume>
		<coor>[31.901205503420883, 118.77167401449809]</coor>
	</detector>
	<detector id="442">
		<volume>9.6</volume>
		<coor>[31.901471170847742, 118.7721006177199]</coor>
	</detector>
	<detector id="443">
		<volume>0.5</volume>
		<coor>[31.90173683827461, 118.7725272209417]</coor>
	</detector>
	<detector id="444">
		<volume>0.5</volume>
		<coor>[31.902002505701468, 118.7729538241635]</coor>
	</detector>
	<detector id="445">
		<volume>0.5</volume>
		<coor>[31.902268173128334, 118.77338042738529]</coor>
	</detector>
	<detector id="446">
		<volume>0.5</volume>
		<coor>[31.902533840555193, 118.77380703060709]</coor>
	</detector>
	<detector id="447">
		<volume>0.5</volume>
		<coor>[31.90279950798206, 118.77423363382889]</coor>
	</detector>
	<detector id="448">
		<volume>0.5</volume>
		<coor>[31.90306517540892, 118.77466023705068]</coor>
	</detector>
	<detector id="449">
		<volume>7.3</volume>
		<coor>[31.90333084283578, 118.77508684027248]</coor>
	</detector>
	<detector id="450">
		<volume>0.5</volume>
		<coor>[31.903596510262645, 118.77551344349428]</coor>
	</detector>
	<detector id="451">
		<volume>0.5</volume>
		<coor>[31.903862177689504, 118.77594004671607]</coor>
	</detector>
	<detector id="452">
		<volume>0.5</volume>
		<coor>[31.90412784511637, 118.77636664993787]</coor>
	</detector>
	<detector id="453">
		<volume>0.5</volume>
		<coor>[31.90439351254323, 118.77679325315967]</coor>
	</detector>
	<detector id="454">
		<volume>1.4</volume>
		<coor>[31.90458857312833, 118.77710647738527]</coor>
	</detector>
	<detector id="455">
		<volume>0.8</volume>
		<coor>[31.895472877783135, 118.77431635175692]</coor>
	</detector>
	<detector id="456">
		<volume>0.8</volume>
		<coor>[31.895139033349395, 118.77467025527078]</coor>
	</detector>
	<detector id="457">
		<volume>0.8</volume>
		<coor>[31.89480518891566, 118.77502415878463]</coor>
	</detector>
	<detector id="458">
		<volume>1.4</volume>
		<coor>[31.89447134448192, 118.77537806229849]</coor>
	</detector>
	<detector id="459">
		<volume>5.0</volume>
		<coor>[31.89413750004819, 118.77573196581234]</coor>
	</detector>
	<detector id="460">
		<volume>9.6</volume>
		<coor>[31.893803655614448, 118.77608586932618]</coor>
	</detector>
	<detector id="461">
		<volume>0.5</volume>
		<coor>[31.893469811180715, 118.77643977284004]</coor>
	</detector>
	<detector id="462">
		<volume>0.5</volume>
		<coor>[31.893135966746975, 118.77679367635389]</coor>
	</detector>
	<detector id="463">
		<volume>0.5</volume>
		<coor>[31.892802122313242, 118.77714757986774]</coor>
	</detector>
	<detector id="464">
		<volume>0.5</volume>
		<coor>[31.8924682778795, 118.7775014833816]</coor>
	</detector>
	<detector id="465">
		<volume>0.5</volume>
		<coor>[31.89213443344577, 118.77785538689545]</coor>
	</detector>
	<detector id="466">
		<volume>0.5</volume>
		<coor>[31.89180058901203, 118.77820929040931]</coor>
	</detector>
	<detector id="467">
		<volume>7.3</volume>
		<coor>[31.891466744578295, 118.77856319392316]</coor>
	</detector>
	<detector id="468">
		<volume>0.5</volume>
		<coor>[31.891132900144555, 118.77891709743702]</coor>
	</detector>
	<detector id="469">
		<volume>0.5</volume>
		<coor>[31.890799055710822, 118.77927100095087]</coor>
	</detector>
	<detector id="470">
		<volume>0.5</volume>
		<coor>[31.890465211277082, 118.77962490446473]</coor>
	</detector>
	<detector id="471">
		<volume>0.5</volume>
		<coor>[31.89013136684334, 118.77997880797858]</coor>
	</detector>
	<detector id="472">
		<volume>1.4</volume>
		<coor>[31.88979752240961, 118.78033271149242]</coor>
	</detector>
	<detector id="473">
		<volume>10.7</volume>
		<coor>[31.88946367797587, 118.78068661500627]</coor>
	</detector>
	<detector id="474">
		<volume>12.2</volume>
		<coor>[31.889129833542135, 118.78104051852013]</coor>
	</detector>
	<detector id="475">
		<volume>0.5</volume>
		<coor>[31.888795989108395, 118.78139442203398]</coor>
	</detector>
	<detector id="476">
		<volume>0.5</volume>
		<coor>[31.888462144674662, 118.78174832554784]</coor>
	</detector>
	<detector id="477">
		<volume>0.5</volume>
		<coor>[31.888128300240922, 118.78210222906169]</coor>
	</detector>
	<detector id="478">
		<volume>0.5</volume>
		<coor>[31.88779445580719, 118.78245613257555]</coor>
	</detector>
	<detector id="479">
		<volume>0.5</volume>
		<coor>[31.88746061137345, 118.7828100360894]</coor>
	</detector>
	<detector id="480">
		<volume>0.5</volume>
		<coor>[31.887126766939716, 118.78316393960326]</coor>
	</detector>
	<detector id="481">
		<volume>0.5</volume>
		<coor>[31.886792922505975, 118.78351784311711]</coor>
	</detector>
	<detector id="482">
		<volume>0.5</volume>
		<coor>[31.886459078072242, 118.78387174663095]</coor>
	</detector>
	<detector id="483">
		<volume>0.5</volume>
		<coor>[31.886231027927685, 118.78411349919394]</coor>
	</detector>
	<detector id="484">
		<volume>0.8</volume>
		<coor>[31.897845844453325, 118.7719258381045]</coor>
	</detector>
	<detector id="485">
		<volume>0.8</volume>
		<coor>[31.89750393335997, 118.77226891431347]</coor>
	</detector>
	<detector id="486">
		<volume>0.8</volume>
		<coor>[31.89716202226662, 118.77261199052245]</coor>
	</detector>
	<detector id="487">
		<volume>1.4</volume>
		<coor>[31.89682011117327, 118.77295506673144]</coor>
	</detector>
	<detector id="488">
		<volume>5.0</volume>
		<coor>[31.89647820007992, 118.77329814294043]</coor>
	</detector>
	<detector id="489">
		<volume>9.6</volume>
		<coor>[31.896136288986565, 118.7736412191494]</coor>
	</detector>
	<detector id="490">
		<volume>0.5</volume>
		<coor>[31.895802566719944, 118.77397607862694]</coor>
	</detector>
	<detector id="491">
		<volume>0.8</volume>
		<coor>[31.899839043029363, 118.76992584020735]</coor>
	</detector>
	<detector id="492">
		<volume>0.8</volume>
		<coor>[31.899497129088083, 118.77026892062204]</coor>
	</detector>
	<detector id="493">
		<volume>0.8</volume>
		<coor>[31.899155215146806, 118.77061200103672]</coor>
	</detector>
	<detector id="494">
		<volume>1.4</volume>
		<coor>[31.89881330120553, 118.7709550814514]</coor>
	</detector>
	<detector id="495">
		<volume>5.0</volume>
		<coor>[31.898471387264248, 118.7712981618661]</coor>
	</detector>
	<detector id="496">
		<volume>9.6</volume>
		<coor>[31.898158615146805, 118.77161200103671]</coor>
	</detector>
	<detector id="497">
		<volume>0.8</volume>
		<coor>[31.910678609751976, 118.76436286690694]</coor>
	</detector>
	<detector id="498">
		<volume>0.8</volume>
		<coor>[31.910754429255928, 118.76488440072083]</coor>
	</detector>
	<detector id="499">
		<volume>0.8</volume>
		<coor>[31.91083024875988, 118.76540593453473]</coor>
	</detector>
	<detector id="500">
		<volume>1.4</volume>
		<coor>[31.910906068263834, 118.76592746834861]</coor>
	</detector>
	<detector id="501">
		<volume>5.0</volume>
		<coor>[31.91098188776779, 118.76644900216249]</coor>
	</detector>
	<detector id="502">
		<volume>9.6</volume>
		<coor>[31.911057707271738, 118.76697053597638]</coor>
	</detector>
	<detector id="503">
		<volume>0.5</volume>
		<coor>[31.911133526775693, 118.76749206979028]</coor>
	</detector>
	<detector id="504">
		<volume>0.5</volume>
		<coor>[31.911209346279648, 118.76801360360415]</coor>
	</detector>
	<detector id="505">
		<volume>0.5</volume>
		<coor>[31.9112851657836, 118.76853513741804]</coor>
	</detector>
	<detector id="506">
		<volume>0.5</volume>
		<coor>[31.91136098528755, 118.76905667123194]</coor>
	</detector>
	<detector id="507">
		<volume>0.5</volume>
		<coor>[31.911436804791506, 118.76957820504582]</coor>
	</detector>
	<detector id="508">
		<volume>0.5</volume>
		<coor>[31.911512624295458, 118.7700997388597]</coor>
	</detector>
	<detector id="509">
		<volume>7.3</volume>
		<coor>[31.91158844379941, 118.7706212726736]</coor>
	</detector>
	<detector id="510">
		<volume>0.5</volume>
		<coor>[31.911664263303365, 118.77114280648749]</coor>
	</detector>
	<detector id="511">
		<volume>0.5</volume>
		<coor>[31.91174008280732, 118.77166434030136]</coor>
	</detector>
	<detector id="512">
		<volume>0.5</volume>
		<coor>[31.91181590231127, 118.77218587411525]</coor>
	</detector>
	<detector id="513">
		<volume>0.5</volume>
		<coor>[31.911891721815223, 118.77270740792915]</coor>
	</detector>
	<detector id="514">
		<volume>1.4</volume>
		<coor>[31.91196754131918, 118.77322894174303]</coor>
	</detector>
	<detector id="515">
		<volume>10.7</volume>
		<coor>[31.91204336082313, 118.77375047555691]</coor>
	</detector>
	<detector id="516">
		<volume>12.2</volume>
		<coor>[31.912119180327082, 118.7742720093708]</coor>
	</detector>
	<detector id="517">
		<volume>0.5</volume>
		<coor>[31.912194999831037, 118.7747935431847]</coor>
	</detector>
	<detector id="518">
		<volume>0.5</volume>
		<coor>[31.912270819334992, 118.77531507699857]</coor>
	</detector>
	<detector id="519">
		<volume>0.5</volume>
		<coor>[31.91234061454348, 118.77579517195275]</coor>
	</detector>
	<detector id="520">
		<volume>0.8</volume>
		<coor>[31.910152684947207, 118.75982030737615]</coor>
	</detector>
	<detector id="521">
		<volume>0.8</volume>
		<coor>[31.910212454841616, 118.76034472212842]</coor>
	</detector>
	<detector id="522">
		<volume>0.8</volume>
		<coor>[31.910272224736026, 118.7608691368807]</coor>
	</detector>
	<detector id="523">
		<volume>1.4</volume>
		<coor>[31.91033199463044, 118.76139355163298]</coor>
	</detector>
	<detector id="524">
		<volume>5.0</volume>
		<coor>[31.910391764524853, 118.76191796638527]</coor>
	</detector>
	<detector id="525">
		<volume>9.6</volume>
		<coor>[31.910451534419263, 118.76244238113755]</coor>
	</detector>
	<detector id="526">
		<volume>0.5</volume>
		<coor>[31.910511304313673, 118.76296679588982]</coor>
	</detector>
	<detector id="527">
		<volume>0.5</volume>
		<coor>[31.910571074208086, 118.7634912106421]</coor>
	</detector>
	<detector id="528">
		<volume>0.5</volume>
		<coor>[31.910620829577645, 118.76392775900912]</coor>
	</detector>
	<detector id="529">
		<volume>0.8</volume>
		<coor>[31.909621805952142, 118.7559451980242]</coor>
	</detector>
	<detector id="530">
		<volume>0.8</volume>
		<coor>[31.909694217856426, 118.75646739407262]</coor>
	</detector>
	<detector id="531">
		<volume>0.8</volume>
		<coor>[31.909766629760714, 118.75698959012101]</coor>
	</detector>
	<detector id="532">
		<volume>1.4</volume>
		<coor>[31.909839041665002, 118.75751178616942]</coor>
	</detector>
	<detector id="533">
		<volume>5.0</volume>
		<coor>[31.909911453569286, 118.75803398221782]</coor>
	</detector>
	<detector id="534">
		<volume>9.6</volume>
		<coor>[31.90998386547357, 118.75855617826622]</coor>
	</detector>
	<detector id="535">
		<volume>0.5</volume>
		<coor>[31.910056277377855, 118.75907837431464]</coor>
	</detector>
	<detector id="536">
		<volume>0.5</volume>
		<coor>[31.910107641665, 118.75944878616943]</coor>
	</detector>
	<detector id="537">
		<volume>0.8</volume>
		<coor>[31.9121498246651, 118.77604887154146]</coor>
	</detector>
	<detector id="538">
		<volume>0.8</volume>
		<coor>[31.9117044739953, 118.77611761462438]</coor>
	</detector>
	<detector id="539">
		<volume>0.8</volume>
		<coor>[31.911259123325504, 118.77618635770729]</coor>
	</detector>
	<detector id="540">
		<volume>1.4</volume>
		<coor>[31.910813772655704, 118.7762551007902]</coor>
	</detector>
	<detector id="541">
		<volume>5.0</volume>
		<coor>[31.910368421985904, 118.77632384387312]</coor>
	</detector>
	<detector id="542">
		<volume>9.6</volume>
		<coor>[31.909923071316108, 118.77639258695604]</coor>
	</detector>
	<detector id="543">
		<volume>0.5</volume>
		<coor>[31.909477720646308, 118.77646133003894]</coor>
	</detector>
	<detector id="544">
		<volume>0.5</volume>
		<coor>[31.909032369976508, 118.77653007312185]</coor>
	</detector>
	<detector id="545">
		<volume>0.5</volume>
		<coor>[31.908587019306708, 118.77659881620477]</coor>
	</detector>
	<detector id="546">
		<volume>0.5</volume>
		<coor>[31.90814166863691, 118.77666755928769]</coor>
	</detector>
	<detector id="547">
		<volume>0.5</volume>
		<coor>[31.907696317967112, 118.7767363023706]</coor>
	</detector>
	<detector id="548">
		<volume>0.5</volume>
		<coor>[31.907250967297315, 118.7768050454535]</coor>
	</detector>
	<detector id="549">
		<volume>7.3</volume>
		<coor>[31.906805616627516, 118.77687378853642]</coor>
	</detector>
	<detector id="550">
		<volume>0.5</volume>
		<coor>[31.906360265957716, 118.77694253161934]</coor>
	</detector>
	<detector id="551">
		<volume>0.5</volume>
		<coor>[31.905914915287916, 118.77701127470225]</coor>
	</detector>
	<detector id="552">
		<volume>0.5</volume>
		<coor>[31.905469564618116, 118.77708001778515]</coor>
	</detector>
	<detector id="553">
		<volume>0.5</volume>
		<coor>[31.90502421394832, 118.77714876086807]</coor>
	</detector>
	<detector id="554">
		<volume>1.4</volume>
		<coor>[31.90472616930671, 118.77719476620476]</coor>
	</detector>
	<detector id="555">
		<volume>0.8</volume>
		<coor>[31.910436006104455, 118.76421093298714]</coor>
	</detector>
	<detector id="556">
		<volume>0.8</volume>
		<coor>[31.910026618313367, 118.76442859896142]</coor>
	</detector>
	<detector id="557">
		<volume>0.8</volume>
		<coor>[31.90961723052228, 118.7646462649357]</coor>
	</detector>
	<detector id="558">
		<volume>1.4</volume>
		<coor>[31.90920784273119, 118.76486393090998]</coor>
	</detector>
	<detector id="559">
		<volume>5.0</volume>
		<coor>[31.9087984549401, 118.76508159688427]</coor>
	</detector>
	<detector id="560">
		<volume>9.6</volume>
		<coor>[31.908389067149013, 118.76529926285855]</coor>
	</detector>
	<detector id="561">
		<volume>0.5</volume>
		<coor>[31.907979679357926, 118.76551692883282]</coor>
	</detector>
	<detector id="562">
		<volume>0.5</volume>
		<coor>[31.907570291566834, 118.76573459480711]</coor>
	</detector>
	<detector id="563">
		<volume>0.5</volume>
		<coor>[31.907160903775747, 118.76595226078139]</coor>
	</detector>
	<detector id="564">
		<volume>0.5</volume>
		<coor>[31.90675151598466, 118.76616992675568]</coor>
	</detector>
	<detector id="565">
		<volume>0.5</volume>
		<coor>[31.90634212819357, 118.76638759272996]</coor>
	</detector>
	<detector id="566">
		<volume>0.5</volume>
		<coor>[31.905932740402484, 118.76660525870423]</coor>
	</detector>
	<detector id="567">
		<volume>7.3</volume>
		<coor>[31.905523352611397, 118.76682292467851]</coor>
	</detector>
	<detector id="568">
		<volume>0.5</volume>
		<coor>[31.90511396482031, 118.7670405906528]</coor>
	</detector>
	<detector id="569">
		<volume>0.5</volume>
		<coor>[31.904704577029218, 118.76725825662709]</coor>
	</detector>
	<detector id="570">
		<volume>0.5</volume>
		<coor>[31.90429518923813, 118.76747592260136]</coor>
	</detector>
	<detector id="571">
		<volume>0.5</volume>
		<coor>[31.903885801447043, 118.76769358857564]</coor>
	</detector>
	<detector id="572">
		<volume>1.4</volume>
		<coor>[31.903476413655955, 118.76791125454992]</coor>
	</detector>
	<detector id="573">
		<volume>10.7</volume>
		<coor>[31.903067025864864, 118.7681289205242]</coor>
	</detector>
	<detector id="574">
		<volume>12.2</volume>
		<coor>[31.902657638073777, 118.76834658649848]</coor>
	</detector>
	<detector id="575">
		<volume>0.5</volume>
		<coor>[31.90224825028269, 118.76856425247277]</coor>
	</detector>
	<detector id="576">
		<volume>0.5</volume>
		<coor>[31.9018388624916, 118.76878191844705]</coor>
	</detector>
	<detector id="577">
		<volume>0.5</volume>
		<coor>[31.901429474700514, 118.76899958442132]</coor>
	</detector>
	<detector id="578">
		<volume>0.5</volume>
		<coor>[31.901020086909426, 118.7692172503956]</coor>
	</detector>
	<detector id="579">
		<volume>0.5</volume>
		<coor>[31.900610699118335, 118.76943491636989]</coor>
	</detector>
	<detector id="580">
		<volume>0.5</volume>
		<coor>[31.900208002611397, 118.76964902467851]</coor>
	</detector>
	<detector id="581">
		<volume>0.8</volume>
		<coor>[31.909690450736154, 118.7553229923949]</coor>
	</detector>
	<detector id="582">
		<volume>0.8</volume>
		<coor>[31.910087752208455, 118.7550761771847]</coor>
	</detector>
	<detector id="583">
		<volume>0.8</volume>
		<coor>[31.91048505368076, 118.75482936197452]</coor>
	</detector>
	<detector id="584">
		<volume>1.4</volume>
		<coor>[31.910882355153063, 118.75458254676431]</coor>
	</detector>
	<detector id="585">
		<volume>5.0</volume>
		<coor>[31.911279656625364, 118.75433573155412]</coor>
	</detector>
	<detector id="586">
		<volume>9.6</volume>
		<coor>[31.911676958097665, 118.75408891634393]</coor>
	</detector>
	<detector id="587">
		<volume>0.5</volume>
		<coor>[31.91207425956997, 118.75384210113373]</coor>
	</detector>
	<detector id="588">
		<volume>0.5</volume>
		<coor>[31.912471561042274, 118.75359528592352]</coor>
	</detector>
	<detector id="589">
		<volume>0.5</volume>
		<coor>[31.912868862514575, 118.75334847071335]</coor>
	</detector>
	<detector id="590">
		<volume>0.5</volume>
		<coor>[31.913266163986876, 118.75310165550314]</coor>
	</detector>
	<detector id="591">
		<volume>0.5</volume>
		<coor>[31.91366346545918, 118.75285484029294]</coor>
	</detector>
	<detector id="592">
		<volume>0.5</volume>
		<coor>[31.914060766931485, 118.75260802508276]</coor>
	</detector>
	<detector id="593">
		<volume>7.3</volume>
		<coor>[31.914458068403786, 118.75236120987256]</coor>
	</detector>
	<detector id="594">
		<volume>0.5</volume>
		<coor>[31.914855369876086, 118.75211439466236]</coor>
	</detector>
	<detector id="595">
		<volume>0.5</volume>
		<coor>[31.91525267134839, 118.75186757945218]</coor>
	</detector>
	<detector id="596">
		<volume>0.5</volume>
		<coor>[31.915649972820695, 118.75162076424198]</coor>
	</detector>
	<detector id="597">
		<volume>0.5</volume>
		<coor>[31.916047274292996, 118.75137394903177]</coor>
	</detector>
	<detector id="598">
		<volume>1.4</volume>
		<coor>[31.916444575765297, 118.75112713382158]</coor>
	</detector>
	<detector id="599">
		<volume>10.7</volume>
		<coor>[31.916695563250727, 118.75097121310824]</coor>
	</detector>
	<detector id="600">
		<volume>0.8</volume>
		<coor>[31.897721914388118, 118.76045097920928]</coor>
	</detector>
	<detector id="601">
		<volume>0.8</volume>
		<coor>[31.897295543164347, 118.76061733762782]</coor>
	</detector>
	<detector id="602">
		<volume>0.8</volume>
		<coor>[31.89686917194058, 118.76078369604639]</coor>
	</detector>
	<detector id="603">
		<volume>1.4</volume>
		<coor>[31.896442800716812, 118.76095005446493]</coor>
	</detector>
	<detector id="604">
		<volume>5.0</volume>
		<coor>[31.89601642949304, 118.7611164128835]</coor>
	</detector>
	<detector id="605">
		<volume>9.6</volume>
		<coor>[31.89559005826927, 118.76128277130204]</coor>
	</detector>
	<detector id="606">
		<volume>0.5</volume>
		<coor>[31.895163687045503, 118.7614491297206]</coor>
	</detector>
	<detector id="607">
		<volume>0.5</volume>
		<coor>[31.894737315821736, 118.76161548813914]</coor>
	</detector>
	<detector id="608">
		<volume>0.5</volume>
		<coor>[31.894310944597965, 118.76178184655771]</coor>
	</detector>
	<detector id="609">
		<volume>0.5</volume>
		<coor>[31.893884573374194, 118.76194820497628]</coor>
	</detector>
	<detector id="610">
		<volume>0.5</volume>
		<coor>[31.893458202150427, 118.76211456339482]</coor>
	</detector>
	<detector id="611">
		<volume>0.5</volume>
		<coor>[31.89303183092666, 118.76228092181339]</coor>
	</detector>
	<detector id="612">
		<volume>7.3</volume>
		<coor>[31.89260545970289, 118.76244728023192]</coor>
	</detector>
	<detector id="613">
		<volume>0.5</volume>
		<coor>[31.892179088479118, 118.76261363865049]</coor>
	</detector>
	<detector id="614">
		<volume>0.5</volume>
		<coor>[31.89175271725535, 118.76277999706903]</coor>
	</detector>
	<detector id="615">
		<volume>0.5</volume>
		<coor>[31.891326346031583, 118.7629463554876]</coor>
	</detector>
	<detector id="616">
		<volume>0.5</volume>
		<coor>[31.890899974807812, 118.76311271390614]</coor>
	</detector>
	<detector id="617">
		<volume>1.4</volume>
		<coor>[31.89047360358404, 118.7632790723247]</coor>
	</detector>
	<detector id="618">
		<volume>10.7</volume>
		<coor>[31.890047232360274, 118.76344543074325]</coor>
	</detector>
	<detector id="619">
		<volume>12.2</volume>
		<coor>[31.889620861136507, 118.76361178916181]</coor>
	</detector>
	<detector id="620">
		<volume>0.5</volume>
		<coor>[31.889194489912736, 118.76377814758035]</coor>
	</detector>
	<detector id="621">
		<volume>0.5</volume>
		<coor>[31.888768118688965, 118.76394450599892]</coor>
	</detector>
	<detector id="622">
		<volume>0.5</volume>
		<coor>[31.888341747465198, 118.76411086441746]</coor>
	</detector>
	<detector id="623">
		<volume>0.5</volume>
		<coor>[31.88791537624143, 118.76427722283603]</coor>
	</detector>
	<detector id="624">
		<volume>0.5</volume>
		<coor>[31.88748900501766, 118.76444358125457]</coor>
	</detector>
	<detector id="625">
		<volume>0.5</volume>
		<coor>[31.88719195970289, 118.76455948023192]</coor>
	</detector>
	<detector id="626">
		<volume>0.8</volume>
		<coor>[31.909373058412683, 118.75576954534847]</coor>
	</detector>
	<detector id="627">
		<volume>0.8</volume>
		<coor>[31.90894797523805, 118.75594043604545]</coor>
	</detector>
	<detector id="628">
		<volume>0.8</volume>
		<coor>[31.908522892063413, 118.75611132674243]</coor>
	</detector>
	<detector id="629">
		<volume>1.4</volume>
		<coor>[31.908097808888776, 118.75628221743938]</coor>
	</detector>
	<detector id="630">
		<volume>5.0</volume>
		<coor>[31.907672725714143, 118.75645310813636]</coor>
	</detector>
	<detector id="631">
		<volume>9.6</volume>
		<coor>[31.90724764253951, 118.75662399883333]</coor>
	</detector>
	<detector id="632">
		<volume>0.5</volume>
		<coor>[31.906822559364876, 118.75679488953028]</coor>
	</detector>
	<detector id="633">
		<volume>0.5</volume>
		<coor>[31.90639747619024, 118.75696578022726]</coor>
	</detector>
	<detector id="634">
		<volume>0.5</volume>
		<coor>[31.905972393015606, 118.75713667092424]</coor>
	</detector>
	<detector id="635">
		<volume>0.5</volume>
		<coor>[31.90554730984097, 118.7573075616212]</coor>
	</detector>
	<detector id="636">
		<volume>0.5</volume>
		<coor>[31.905122226666336, 118.75747845231817]</coor>
	</detector>
	<detector id="637">
		<volume>0.5</volume>
		<coor>[31.904697143491703, 118.75764934301515]</coor>
	</detector>
	<detector id="638">
		<volume>7.3</volume>
		<coor>[31.904272060317066, 118.75782023371211]</coor>
	</detector>
	<detector id="639">
		<volume>0.5</volume>
		<coor>[31.903846977142432, 118.75799112440907]</coor>
	</detector>
	<detector id="640">
		<volume>0.5</volume>
		<coor>[31.903421893967796, 118.75816201510605]</coor>
	</detector>
	<detector id="641">
		<volume>0.5</volume>
		<coor>[31.902996810793162, 118.75833290580302]</coor>
	</detector>
	<detector id="642">
		<volume>0.5</volume>
		<coor>[31.90257172761853, 118.75850379649998]</coor>
	</detector>
	<detector id="643">
		<volume>1.4</volume>
		<coor>[31.902146644443892, 118.75867468719696]</coor>
	</detector>
	<detector id="644">
		<volume>10.7</volume>
		<coor>[31.90172156126926, 118.75884557789392]</coor>
	</detector>
	<detector id="645">
		<volume>12.2</volume>
		<coor>[31.901296478094622, 118.75901646859089]</coor>
	</detector>
	<detector id="646">
		<volume>0.5</volume>
		<coor>[31.90087139491999, 118.75918735928786]</coor>
	</detector>
	<detector id="647">
		<volume>0.5</volume>
		<coor>[31.900446311745355, 118.75935824998483]</coor>
	</detector>
	<detector id="648">
		<volume>0.5</volume>
		<coor>[31.90002122857072, 118.75952914068179]</coor>
	</detector>
	<detector id="649">
		<volume>0.5</volume>
		<coor>[31.899596145396085, 118.75970003137877]</coor>
	</detector>
	<detector id="650">
		<volume>0.5</volume>
		<coor>[31.89917106222145, 118.75987092207573]</coor>
	</detector>
	<detector id="651">
		<volume>0.5</volume>
		<coor>[31.898745979046815, 118.7600418127727]</coor>
	</detector>
	<detector id="652">
		<volume>0.5</volume>
		<coor>[31.898320895872182, 118.76021270346968]</coor>
	</detector>
	<detector id="653">
		<volume>0.5</volume>
		<coor>[31.898021727142435, 118.76033297440908]</coor>
	</detector>
	<detector id="654">
		<volume>0.8</volume>
		<coor>[31.88722118056543, 118.76482071926861]</coor>
	</detector>
	<detector id="655">
		<volume>0.8</volume>
		<coor>[31.887447341696294, 118.76527775780582]</coor>
	</detector>
	<detector id="656">
		<volume>0.8</volume>
		<coor>[31.887673502827155, 118.76573479634305]</coor>
	</detector>
	<detector id="657">
		<volume>1.4</volume>
		<coor>[31.887899663958017, 118.76619183488026]</coor>
	</detector>
	<detector id="658">
		<volume>5.0</volume>
		<coor>[31.88812582508888, 118.7666488734175]</coor>
	</detector>
	<detector id="659">
		<volume>9.6</volume>
		<coor>[31.888351986219746, 118.7671059119547]</coor>
	</detector>
	<detector id="660">
		<volume>0.5</volume>
		<coor>[31.88850588339259, 118.76741691561166]</coor>
	</detector>
	<detector id="661">
		<volume>0.8</volume>
		<coor>[31.888719732255144, 118.76766801353997]</coor>
	</detector>
	<detector id="662">
		<volume>0.8</volume>
		<coor>[31.889065796765436, 118.76800524061993]</coor>
	</detector>
	<detector id="663">
		<volume>0.8</volume>
		<coor>[31.889411861275725, 118.76834246769988]</coor>
	</detector>
	<detector id="664">
		<volume>1.4</volume>
		<coor>[31.889757925786014, 118.76867969477982]</coor>
	</detector>
	<detector id="665">
		<volume>5.0</volume>
		<coor>[31.890103990296307, 118.76901692185976]</coor>
	</detector>
	<detector id="666">
		<volume>9.6</volume>
		<coor>[31.8904500548066, 118.76935414893973]</coor>
	</detector>
	<detector id="667">
		<volume>0.5</volume>
		<coor>[31.89079611931689, 118.76969137601967]</coor>
	</detector>
	<detector id="668">
		<volume>0.5</volume>
		<coor>[31.891142183827178, 118.7700286030996]</coor>
	</detector>
	<detector id="669">
		<volume>0.5</volume>
		<coor>[31.89148824833747, 118.77036583017957]</coor>
	</detector>
	<detector id="670">
		<volume>0.5</volume>
		<coor>[31.891834312847763, 118.77070305725951]</coor>
	</detector>
	<detector id="671">
		<volume>0.5</volume>
		<coor>[31.892180377358052, 118.77104028433945]</coor>
	</detector>
	<detector id="672">
		<volume>0.5</volume>
		<coor>[31.89252644186834, 118.7713775114194]</coor>
	</detector>
	<detector id="673">
		<volume>7.3</volume>
		<coor>[31.892864937061745, 118.77170736247969]</coor>
	</detector>
	<detector id="674">
		<volume>0.8</volume>
		<coor>[31.893211024862637, 118.77202578668586]</coor>
	</detector>
	<detector id="675">
		<volume>0.8</volume>
		<coor>[31.893572274587918, 118.77234016005758]</coor>
	</detector>
	<detector id="676">
		<volume>0.8</volume>
		<coor>[31.89393352431319, 118.77265453342929]</coor>
	</detector>
	<detector id="677">
		<volume>1.4</volume>
		<coor>[31.894294774038464, 118.772968906801]</coor>
	</detector>
	<detector id="678">
		<volume>5.0</volume>
		<coor>[31.894656023763744, 118.77328328017272]</coor>
	</detector>
	<detector id="679">
		<volume>9.6</volume>
		<coor>[31.895017273489017, 118.77359765354444]</coor>
	</detector>
	<detector id="680">
		<volume>0.5</volume>
		<coor>[31.895378523214298, 118.77391202691615]</coor>
	</detector>
	<detector id="681">
		<volume>0.5</volume>
		<coor>[31.89559947403847, 118.77410430680101]</coor>
	</detector>
	<detector id="682">
		<volume>0.8</volume>
		<coor>[31.904413783141433, 118.77723853558581]</coor>
	</detector>
	<detector id="683">
		<volume>0.8</volume>
		<coor>[31.903953660537177, 118.77730092063945]</coor>
	</detector>
	<detector id="684">
		<volume>0.8</volume>
		<coor>[31.903507449045804, 118.77736141957507]</coor>
	</detector>
	<detector id="685">
		<volume>1.4</volume>
		<coor>[31.903061237554425, 118.77742191851073]</coor>
	</detector>
	<detector id="686">
		<volume>5.0</volume>
		<coor>[31.902615026063046, 118.77748241744635]</coor>
	</detector>
	<detector id="687">
		<volume>9.6</volume>
		<coor>[31.902168814571674, 118.77754291638198]</coor>
	</detector>
	<detector id="688">
		<volume>0.5</volume>
		<coor>[31.901722603080295, 118.77760341531763]</coor>
	</detector>
	<detector id="689">
		<volume>0.5</volume>
		<coor>[31.901276391588922, 118.77766391425325]</coor>
	</detector>
	<detector id="690">
		<volume>0.5</volume>
		<coor>[31.900830180097543, 118.7777244131889]</coor>
	</detector>
	<detector id="691">
		<volume>0.5</volume>
		<coor>[31.900416025338323, 118.77761561409301]</coor>
	</detector>
	<detector id="692">
		<volume>0.5</volume>
		<coor>[31.900033927311256, 118.77733751696556]</coor>
	</detector>
	<detector id="693">
		<volume>0.5</volume>
		<coor>[31.899651829284192, 118.77705941983811]</coor>
	</detector>
	<detector id="694">
		<volume>7.3</volume>
		<coor>[31.899269731257128, 118.77678132271068]</coor>
	</detector>
	<detector id="695">
		<volume>0.5</volume>
		<coor>[31.89888763323006, 118.77650322558324]</coor>
	</detector>
	<detector id="696">
		<volume>0.5</volume>
		<coor>[31.898505535202993, 118.77622512845579]</coor>
	</detector>
	<detector id="697">
		<volume>0.5</volume>
		<coor>[31.89812343717593, 118.77594703132836]</coor>
	</detector>
	<detector id="698">
		<volume>0.5</volume>
		<coor>[31.897741339148865, 118.77566893420092]</coor>
	</detector>
	<detector id="699">
		<volume>1.4</volume>
		<coor>[31.897359241121798, 118.77539083707347]</coor>
	</detector>
	<detector id="700">
		<volume>10.7</volume>
		<coor>[31.89697714309473, 118.77511273994604]</coor>
	</detector>
	<detector id="701">
		<volume>12.2</volume>
		<coor>[31.896595045067667, 118.7748346428186]</coor>
	</detector>
	<detector id="702">
		<volume>0.5</volume>
		<coor>[31.896212947040603, 118.77455654569115]</coor>
	</detector>
	<detector id="703">
		<volume>0.5</volume>
		<coor>[31.895830849013535, 118.7742784485637]</coor>
	</detector>
	<detector id="704">
		<volume>0.8</volume>
		<coor>[31.909923543640673, 118.75968013330223]</coor>
	</detector>
	<detector id="705">
		<volume>0.8</volume>
		<coor>[31.909525030922026, 118.75992419990669]</coor>
	</detector>
	<detector id="706">
		<volume>0.8</volume>
		<coor>[31.909126518203372, 118.76016826651116]</coor>
	</detector>
	<detector id="707">
		<volume>1.4</volume>
		<coor>[31.908728005484722, 118.7604123331156]</coor>
	</detector>
	<detector id="708">
		<volume>5.0</volume>
		<coor>[31.90832949276607, 118.76065639972006]</coor>
	</detector>
	<detector id="709">
		<volume>9.6</volume>
		<coor>[31.907930980047418, 118.76090046632453]</coor>
	</detector>
	<detector id="710">
		<volume>0.5</volume>
		<coor>[31.90753246732877, 118.76114453292897]</coor>
	</detector>
	<detector id="711">
		<volume>0.5</volume>
		<coor>[31.907133954610117, 118.76138859953343]</coor>
	</detector>
	<detector id="712">
		<volume>0.5</volume>
		<coor>[31.90673544189147, 118.7616326661379]</coor>
	</detector>
	<detector id="713">
		<volume>0.5</volume>
		<coor>[31.906336929172816, 118.76187673274234]</coor>
	</detector>
	<detector id="714">
		<volume>0.5</volume>
		<coor>[31.905938416454163, 118.7621207993468]</coor>
	</detector>
	<detector id="715">
		<volume>0.5</volume>
		<coor>[31.905539903735516, 118.76236486595126]</coor>
	</detector>
	<detector id="716">
		<volume>7.3</volume>
		<coor>[31.905141391016862, 118.76260893255571]</coor>
	</detector>
	<detector id="717">
		<volume>0.5</volume>
		<coor>[31.904742878298215, 118.76285299916017]</coor>
	</detector>
	<detector id="718">
		<volume>0.5</volume>
		<coor>[31.90434436557956, 118.76309706576463]</coor>
	</detector>
	<detector id="719">
		<volume>0.5</volume>
		<coor>[31.90394585286091, 118.76334113236908]</coor>
	</detector>
	<detector id="720">
		<volume>0.5</volume>
		<coor>[31.90354734014226, 118.76358519897354]</coor>
	</detector>
	<detector id="721">
		<volume>1.4</volume>
		<coor>[31.903148827423607, 118.763829265578]</coor>
	</detector>
	<detector id="722">
		<volume>10.7</volume>
		<coor>[31.90275031470496, 118.76407333218245]</coor>
	</detector>
	<detector id="723">
		<volume>12.2</volume>
		<coor>[31.902351801986306, 118.76431739878691]</coor>
	</detector>
	<detector id="724">
		<volume>0.5</volume>
		<coor>[31.90195328926766, 118.76456146539137]</coor>
	</detector>
	<detector id="725">
		<volume>0.5</volume>
		<coor>[31.901554776549006, 118.76480553199582]</coor>
	</detector>
	<detector id="726">
		<volume>0.5</volume>
		<coor>[31.90115626383035, 118.76504959860029]</coor>
	</detector>
	<detector id="727">
		<volume>0.5</volume>
		<coor>[31.900757751111705, 118.76529366520474]</coor>
	</detector>
	<detector id="728">
		<volume>0.5</volume>
		<coor>[31.90035923839305, 118.76553773180919]</coor>
	</detector>
	<detector id="729">
		<volume>0.5</volume>
		<coor>[31.899960725674404, 118.76578179841366]</coor>
	</detector>
	<detector id="730">
		<volume>0.5</volume>
		<coor>[31.89956221295575, 118.76602586501811]</coor>
	</detector>
	<detector id="731">
		<volume>0.5</volume>
		<coor>[31.8991637002371, 118.76626993162256]</coor>
	</detector>
	<detector id="732">
		<volume>0.5</volume>
		<coor>[31.89876518751845, 118.76651399822703]</coor>
	</detector>
	<detector id="733">
		<volume>0.5</volume>
		<coor>[31.898482765579562, 118.76668696576462]</coor>
	</detector>
	<detector id="734">
		<volume>0.8</volume>
		<coor>[31.898226902724716, 118.7669070012226]</coor>
	</detector>
	<detector id="735">
		<volume>0.8</volume>
		<coor>[31.89788150817415, 118.76724520366781]</coor>
	</detector>
	<detector id="736">
		<volume>0.8</volume>
		<coor>[31.897536113623588, 118.76758340611303]</coor>
	</detector>
	<detector id="737">
		<volume>1.4</volume>
		<coor>[31.89719071907302, 118.76792160855825]</coor>
	</detector>
	<detector id="738">
		<volume>5.0</volume>
		<coor>[31.896845324522452, 118.76825981100346]</coor>
	</detector>
	<detector id="739">
		<volume>9.6</volume>
		<coor>[31.89649992997189, 118.76859801344868]</coor>
	</detector>
	<detector id="740">
		<volume>0.5</volume>
		<coor>[31.896268466348303, 118.76882465733564]</coor>
	</detector>
	<detector id="741">
		<volume>0.8</volume>
		<coor>[31.896034106456625, 118.76904710648941]</coor>
	</detector>
	<detector id="742">
		<volume>0.8</volume>
		<coor>[31.895682919369882, 118.76937691946824]</coor>
	</detector>
	<detector id="743">
		<volume>0.8</volume>
		<coor>[31.89533173228314, 118.76970673244708]</coor>
	</detector>
	<detector id="744">
		<volume>1.4</volume>
		<coor>[31.89498054519639, 118.77003654542591]</coor>
	</detector>
	<detector id="745">
		<volume>5.0</volume>
		<coor>[31.894629358109647, 118.77036635840474]</coor>
	</detector>
	<detector id="746">
		<volume>9.6</volume>
		<coor>[31.8942781710229, 118.77069617138358]</coor>
	</detector>
	<detector id="747">
		<volume>0.5</volume>
		<coor>[31.893926983936154, 118.77102598436241]</coor>
	</detector>
	<detector id="748">
		<volume>0.5</volume>
		<coor>[31.89357579684941, 118.77135579734124]</coor>
	</detector>
	<detector id="749">
		<volume>0.5</volume>
		<coor>[31.89322460976266, 118.77168561032008]</coor>
	</detector>
	<detector id="750">
		<volume>0.5</volume>
		<coor>[31.893039708109647, 118.77185925840475]</coor>
	</detector>
	<detector id="751">
		<volume>0.8</volume>
		<coor>[31.89783482822903, 118.76336063333451]</coor>
	</detector>
	<detector id="752">
		<volume>0.8</volume>
		<coor>[31.89740748468708, 118.76352350000357]</coor>
	</detector>
	<detector id="753">
		<volume>0.8</volume>
		<coor>[31.896980141145136, 118.76368636667263]</coor>
	</detector>
	<detector id="754">
		<volume>1.4</volume>
		<coor>[31.896552797603192, 118.76384923334167]</coor>
	</detector>
	<detector id="755">
		<volume>5.0</volume>
		<coor>[31.89612545406124, 118.76401210001072]</coor>
	</detector>
	<detector id="756">
		<volume>9.6</volume>
		<coor>[31.895698110519298, 118.76417496667978]</coor>
	</detector>
	<detector id="757">
		<volume>0.5</volume>
		<coor>[31.89527076697735, 118.76433783334883]</coor>
	</detector>
	<detector id="758">
		<volume>0.5</volume>
		<coor>[31.894843423435404, 118.76450070001788]</coor>
	</detector>
	<detector id="759">
		<volume>0.5</volume>
		<coor>[31.89441607989346, 118.76466356668692]</coor>
	</detector>
	<detector id="760">
		<volume>0.5</volume>
		<coor>[31.89398873635151, 118.76482643335598]</coor>
	</detector>
	<detector id="761">
		<volume>0.5</volume>
		<coor>[31.89373343229027, 118.76492373334526]</coor>
	</detector>
	<detector id="762">
		<volume>0.8</volume>
		<coor>[31.89348492172936, 118.7650425264732]</coor>
	</detector>
	<detector id="763">
		<volume>0.8</volume>
		<coor>[31.893071165188083, 118.76524837941955]</coor>
	</detector>
	<detector id="764">
		<volume>0.8</volume>
		<coor>[31.892657408646805, 118.76545423236593]</coor>
	</detector>
	<detector id="765">
		<volume>1.4</volume>
		<coor>[31.89224365210553, 118.7656600853123]</coor>
	</detector>
	<detector id="766">
		<volume>5.0</volume>
		<coor>[31.891829895564253, 118.76586593825866]</coor>
	</detector>
	<detector id="767">
		<volume>9.6</volume>
		<coor>[31.891416139022976, 118.76607179120504]</coor>
	</detector>
	<detector id="768">
		<volume>0.5</volume>
		<coor>[31.891002382481698, 118.7662776441514]</coor>
	</detector>
	<detector id="769">
		<volume>0.5</volume>
		<coor>[31.89058862594042, 118.76648349709777]</coor>
	</detector>
	<detector id="770">
		<volume>0.5</volume>
		<coor>[31.890174869399146, 118.76668935004415]</coor>
	</detector>
	<detector id="771">
		<volume>0.5</volume>
		<coor>[31.88976111285787, 118.7668952029905]</coor>
	</detector>
	<detector id="772">
		<volume>0.5</volume>
		<coor>[31.88934735631659, 118.76710105593688]</coor>
	</detector>
	<detector id="773">
		<volume>0.5</volume>
		<coor>[31.888933599775314, 118.76730690888326]</coor>
	</detector>
	<detector id="774">
		<volume>7.3</volume>
		<coor>[31.888636710752337, 118.76745461767823]</coor>
	</detector>
	<detector id="775">
		<volume>0.8</volume>
		<coor>[31.89634341715263, 118.7690947222921]</coor>
	</detector>
	<detector id="776">
		<volume>0.8</volume>
		<coor>[31.89661085145788, 118.7695197668763]</coor>
	</detector>
	<detector id="777">
		<volume>0.8</volume>
		<coor>[31.896878285763137, 118.7699448114605]</coor>
	</detector>
	<detector id="778">
		<volume>1.4</volume>
		<coor>[31.897145720068387, 118.77036985604471]</coor>
	</detector>
	<detector id="779">
		<volume>5.0</volume>
		<coor>[31.897413154373638, 118.77079490062893]</coor>
	</detector>
	<detector id="780">
		<volume>9.6</volume>
		<coor>[31.897680588678895, 118.77121994521313]</coor>
	</detector>
	<detector id="781">
		<volume>0.5</volume>
		<coor>[31.897915552915762, 118.77159338375262]</coor>
	</detector>
	<detector id="782">
		<volume>0.8</volume>
		<coor>[31.893826787810603, 118.76515039995027]</coor>
	</detector>
	<detector id="783">
		<volume>0.8</volume>
		<coor>[31.89409676343182, 118.7655731998508]</coor>
	</detector>
	<detector id="784">
		<volume>0.8</volume>
		<coor>[31.894366739053034, 118.76599599975134]</coor>
	</detector>
	<detector id="785">
		<volume>1.4</volume>
		<coor>[31.894636714674245, 118.76641879965189]</coor>
	</detector>
	<detector id="786">
		<volume>5.0</volume>
		<coor>[31.894906690295457, 118.76684159955242]</coor>
	</detector>
	<detector id="787">
		<volume>9.6</volume>
		<coor>[31.895176665916672, 118.76726439945296]</coor>
	</detector>
	<detector id="788">
		<volume>0.5</volume>
		<coor>[31.895446641537887, 118.7676871993535]</coor>
	</detector>
	<detector id="789">
		<volume>0.5</volume>
		<coor>[31.895716617159096, 118.76810999925404]</coor>
	</detector>
	<detector id="790">
		<volume>0.5</volume>
		<coor>[31.89598659278031, 118.76853279915457]</coor>
	</detector>
	<detector id="791">
		<volume>0.5</volume>
		<coor>[31.896165640295457, 118.76881319955243]</coor>
	</detector>
	<detector id="792">
		<volume>0.8</volume>
		<coor>[31.88688352117897, 118.7645922]</coor>
	</detector>
	<detector id="793">
		<volume>0.8</volume>
		<coor>[31.88643436353691, 118.7645922]</coor>
	</detector>
	<detector id="794">
		<volume>0.8</volume>
		<coor>[31.88598520589485, 118.7645922]</coor>
	</detector>
	<detector id="795">
		<volume>1.4</volume>
		<coor>[31.885536048252792, 118.7645922]</coor>
	</detector>
	<detector id="796">
		<volume>5.0</volume>
		<coor>[31.885086890610733, 118.7645922]</coor>
	</detector>
	<detector id="797">
		<volume>9.6</volume>
		<coor>[31.88463773296867, 118.7645922]</coor>
	</detector>
	<detector id="798">
		<volume>0.5</volume>
		<coor>[31.88418857532661, 118.7645922]</coor>
	</detector>
	<detector id="799">
		<volume>0.5</volume>
		<coor>[31.883739417684552, 118.7645922]</coor>
	</detector>
	<detector id="800">
		<volume>0.5</volume>
		<coor>[31.883290260042493, 118.7645922]</coor>
	</detector>
	<detector id="801">
		<volume>0.5</volume>
		<coor>[31.882841102400434, 118.7645922]</coor>
	</detector>
	<detector id="802">
		<volume>0.5</volume>
		<coor>[31.882391944758375, 118.7645922]</coor>
	</detector>
	<detector id="803">
		<volume>0.5</volume>
		<coor>[31.881942787116316, 118.7645922]</coor>
	</detector>
	<detector id="804">
		<volume>7.3</volume>
		<coor>[31.881493629474257, 118.7645922]</coor>
	</detector>
	<detector id="805">
		<volume>0.5</volume>
		<coor>[31.881044471832197, 118.7645922]</coor>
	</detector>
	<detector id="806">
		<volume>0.5</volume>
		<coor>[31.88059531419014, 118.7645922]</coor>
	</detector>
	<detector id="807">
		<volume>0.5</volume>
		<coor>[31.880235367684556, 118.7645922]</coor>
	</detector>
	<detector id="808">
		<volume>0.8</volume>
		<coor>[31.904764773134524, 118.77743434626905]</coor>
	</detector>
	<detector id="809">
		<volume>0.8</volume>
		<coor>[31.904992719403573, 118.77789023880715]</coor>
	</detector>
	<detector id="810">
		<volume>0.8</volume>
		<coor>[31.905220665672623, 118.77834613134524]</coor>
	</detector>
	<detector id="811">
		<volume>1.4</volume>
		<coor>[31.905448611941672, 118.77880202388336]</coor>
	</detector>
	<detector id="812">
		<volume>5.0</volume>
		<coor>[31.9056066925381, 118.77911818507621]</coor>
	</detector>
	<detector id="813">
		<volume>0.8</volume>
		<coor>[31.912409771213024, 118.77627539849117]</coor>
	</detector>
	<detector id="814">
		<volume>0.8</volume>
		<coor>[31.91248431363907, 118.7767971954735]</coor>
	</detector>
	<detector id="815">
		<volume>0.8</volume>
		<coor>[31.912558856065118, 118.77731899245583]</coor>
	</detector>
	<detector id="816">
		<volume>1.4</volume>
		<coor>[31.912633398491167, 118.77784078943816]</coor>
	</detector>
	<detector id="817">
		<volume>5.0</volume>
		<coor>[31.912707940917215, 118.7783625864205]</coor>
	</detector>
	<detector id="818">
		<volume>9.6</volume>
		<coor>[31.912782483343264, 118.77888438340284]</coor>
	</detector>
	<detector id="819">
		<volume>0.5</volume>
		<coor>[31.91285702576931, 118.77940618038517]</coor>
	</detector>
	<detector id="820">
		<volume>0.5</volume>
		<coor>[31.912931568195358, 118.77992797736749]</coor>
	</detector>
	<detector id="821">
		<volume>0.5</volume>
		<coor>[31.913006110621406, 118.78044977434983]</coor>
	</detector>
	<detector id="822">
		<volume>0.5</volume>
		<coor>[31.91308065304745, 118.78097157133217]</coor>
	</detector>
	<detector id="823">
		<volume>0.5</volume>
		<coor>[31.9131551954735, 118.7814933683145]</coor>
	</detector>
	<detector id="824">
		<volume>0.5</volume>
		<coor>[31.91322973789955, 118.78201516529683]</coor>
	</detector>
	<detector id="825">
		<volume>7.3</volume>
		<coor>[31.913304280325598, 118.78253696227917]</coor>
	</detector>
	<detector id="826">
		<volume>0.5</volume>
		<coor>[31.91335702576931, 118.78290618038517]</coor>
	</detector>
	<detector id="827">
		<volume>0.8</volume>
		<coor>[31.91259707882103, 118.7760145]</coor>
	</detector>
	<detector id="828">
		<volume>0.8</volume>
		<coor>[31.91304623646309, 118.7760145]</coor>
	</detector>
	<detector id="829">
		<volume>0.8</volume>
		<coor>[31.913495394105148, 118.7760145]</coor>
	</detector>
	<detector id="830">
		<volume>1.4</volume>
		<coor>[31.913944551747207, 118.7760145]</coor>
	</detector>
	<detector id="831">
		<volume>5.0</volume>
		<coor>[31.914393709389266, 118.7760145]</coor>
	</detector>
	<detector id="832">
		<volume>9.6</volume>
		<coor>[31.914842867031325, 118.7760145]</coor>
	</detector>
	<detector id="833">
		<volume>0.5</volume>
		<coor>[31.915219972926177, 118.7760145]</coor>
	</detector>
</detectors>
